MODULES/CCM/RTL/src/CCM.v
// all pixels delayed by three clock cycles for pipeline, coef_in read at frame start
module CCM #(
    parameter PIXEL_W = 10,
    parameter LINE_W  = 2048,
    parameter FRAME_W = 1080,
    parameter COEF_W  = 10,
    parameter FRAC_W  = 8
)(
    input clk, resetn,
    input valid_in, h_sync, v_sync, coef_in,
    input[PIXEL_W-1:0] red_in, green_in, blue_in,
    input[(3*COEF_W)-1:0] row0, row1, row2,
    output reg valid_out, h_sync_out, v_sync_out,
    output reg[PIXEL_W-1:0] red_out, green_out, blue_out
);
    localparam MAX_VAL    = (1 << PIXEL_W) - 1;
    localparam MAX_MULT_W = PIXEL_W + COEF_W;
    localparam MAX_DIST_W = MAX_MULT_W + 2;
    localparam DELAY      = 3;
    localparam ROUND_CONST = (FRAC_W > 0) ? (1 <<< (FRAC_W-1)) : 0;

    reg signed[COEF_W-1:0] matrix[2:0][2:0];

    integer i, j;
    always@(posedge clk or negedge resetn) begin
        if(!resetn) begin
            for(i = 0; i < 3; i = i + 1)
                for(j = 0; j < 3; j = j + 1)
                    matrix[i][j] <= 0;

        end 
        else if(coef_in && v_sync) begin
                matrix[0][0] <= row0[COEF_W-1:0];
                matrix[0][1] <= row0[2*COEF_W-1:COEF_W];
                matrix[0][2] <= row0[3*COEF_W-1:2*COEF_W];

                matrix[1][0] <= row1[COEF_W-1:0];
                matrix[1][1] <= row1[2*COEF_W-1:COEF_W];
                matrix[1][2] <= row1[3*COEF_W-1:2*COEF_W];

                matrix[2][0] <= row2[COEF_W-1:0];
                matrix[2][1] <= row2[2*COEF_W-1:COEF_W];
                matrix[2][2] <= row2[3*COEF_W-1:2*COEF_W];
        end
    end
    
    reg[DELAY-1:0] valid_pipe, h_pipe, v_pipe;
    
    reg signed[PIXEL_W:0] red_pipe, green_pipe, blue_pipe; 

    reg signed[MAX_MULT_W-1:0] red_mult[2:0], green_mult[2:0], blue_mult[2:0];
    reg signed[MAX_DIST_W-1:0] red_dist, green_dist, blue_dist;

    wire signed[MAX_DIST_W:0] red_dist_rnd   = {red_dist[MAX_DIST_W-1],   red_dist}   + ROUND_CONST;
    wire signed[MAX_DIST_W:0] green_dist_rnd = {green_dist[MAX_DIST_W-1], green_dist} + ROUND_CONST;
    wire signed[MAX_DIST_W:0] blue_dist_rnd  = {blue_dist[MAX_DIST_W-1],  blue_dist}  + ROUND_CONST;

    always@(posedge clk or negedge resetn) begin
        if(!resetn) begin
            valid_out  <= 0;
            h_sync_out <= 0;
            v_sync_out <= 0;
            red_out    <= 0;
            green_out  <= 0;
            blue_out   <= 0;

            valid_pipe <= 0;
            h_pipe     <= 0;
            v_pipe     <= 0;

            red_pipe   <= 0;
            green_pipe <= 0;
            blue_pipe  <= 0;

            for(i = 0; i < 3; i = i + 1) begin
                red_mult[i]   <= 0;
                green_mult[i] <= 0;
                blue_mult[i]  <= 0;
            end

            red_dist   <= 0;
            green_dist <= 0;
            blue_dist  <= 0;

        end 
        else begin
            
            valid_pipe <= {valid_pipe[DELAY-2:0], valid_in};
            h_pipe     <= {h_pipe[DELAY-2:0], h_sync};
            v_pipe     <= {v_pipe[DELAY-2:0], v_sync};

            valid_out  <= valid_pipe[DELAY-1];
            h_sync_out <= h_pipe[DELAY-1];
            v_sync_out <= v_pipe[DELAY-1];

            if(valid_in) begin
                red_pipe   <= {1'b0, red_in};
                green_pipe <= {1'b0, green_in};
                blue_pipe  <= {1'b0, blue_in};
            end

            if(valid_pipe[0]) begin
                red_mult[0] <= red_pipe   * matrix[0][0];
                red_mult[1] <= green_pipe * matrix[0][1];
                red_mult[2] <= blue_pipe  * matrix[0][2];

                green_mult[0] <= red_pipe   * matrix[1][0];
                green_mult[1] <= green_pipe * matrix[1][1];
                green_mult[2] <= blue_pipe  * matrix[1][2];

                blue_mult[0] <= red_pipe   * matrix[2][0];
                blue_mult[1] <= green_pipe * matrix[2][1];
                blue_mult[2] <= blue_pipe  * matrix[2][2];
            end

            if(valid_pipe[1]) begin
                red_dist   <= red_mult[0]   + red_mult[1]   + red_mult[2];
                green_dist <= green_mult[0] + green_mult[1] + green_mult[2];
                blue_dist  <= blue_mult[0]  + blue_mult[1]  + blue_mult[2];
            end

            if(valid_pipe[2]) begin
                red_out   <= (red_dist_rnd[MAX_DIST_W]) ? 0 :
                             ((red_dist_rnd >>> FRAC_W) > MAX_VAL) ? MAX_VAL : (red_dist_rnd >>> FRAC_W);

                green_out <= (green_dist_rnd[MAX_DIST_W]) ? 0 :
                             ((green_dist_rnd >>> FRAC_W) > MAX_VAL) ? MAX_VAL : (green_dist_rnd >>> FRAC_W);

                blue_out  <= (blue_dist_rnd[MAX_DIST_W]) ? 0 :
                             ((blue_dist_rnd >>> FRAC_W) > MAX_VAL) ? MAX_VAL : (blue_dist_rnd >>> FRAC_W);
            end
        end
    end

endmodule

MODULES/CCM/RTL/src/ccm_tb.v
module ccm_tb();
    localparam PIXEL_W   = 10;
    localparam LINE_W    = 8;
    localparam FRAME_W   = 8;
    localparam COEF_W    = 10;
    localparam FRAC_W    = 8;
    localparam MAX_VAL   = (1 << PIXEL_W) - 1;
    localparam SAT_LEVEL = MAX_VAL;

    localparam MAX_MULT_W = PIXEL_W + COEF_W;
    localparam MAX_DIST_W = MAX_MULT_W + 2;

    reg clk, resetn;
    reg valid_in, h_sync, v_sync, coef_in;
    reg[PIXEL_W-1:0] red_in, green_in, blue_in;
    reg[(3*COEF_W)-1:0] row0, row1, row2;

    wire valid_out, h_sync_out, v_sync_out;
    wire[PIXEL_W-1:0] red_out, green_out, blue_out;

    CCM #(
        .PIXEL_W(PIXEL_W),
        .LINE_W(LINE_W),
        .FRAME_W(FRAME_W),
        .COEF_W(COEF_W),
        .FRAC_W(FRAC_W)
    ) dut (
        .clk(clk),
        .resetn(resetn),
        .valid_in(valid_in),
        .h_sync(h_sync),
        .v_sync(v_sync),
        .coef_in(coef_in),
        .red_in(red_in),
        .green_in(green_in),
        .blue_in(blue_in),
        .row0(row0),
        .row1(row1),
        .row2(row2),
        .valid_out(valid_out),
        .h_sync_out(h_sync_out),
        .v_sync_out(v_sync_out),
        .red_out(red_out),
        .green_out(green_out),
        .blue_out(blue_out)
    );

    initial clk = 0;
    always #1.5 clk = ~clk;

    // Row 0: [ 1.20, -0.10, -0.10] -> [ 307, -26, -26]
    // Row 1: [-0.10,  1.20, -0.10] -> [-26,  307, -26]
    // Row 2: [-0.10, -0.10,  1.20] -> [-26, -26,  307]
    reg signed [COEF_W-1:0] c[2:0][2:0];

    initial begin
        c[0][0] = 10'sd307;  c[0][1] = -10'sd26; c[0][2] = -10'sd26;
        c[1][0] = -10'sd26;  c[1][1] = 10'sd307; c[1][2] = -10'sd26;
        c[2][0] = -10'sd26;  c[2][1] = -10'sd26; c[2][2] = 10'sd307;

        row0 = {c[0][2], c[0][1], c[0][0]};
        row1 = {c[1][2], c[1][1], c[1][0]};
        row2 = {c[2][2], c[2][1], c[2][0]};
    end

    function [PIXEL_W-1:0] calc_expected;
        input[PIXEL_W-1:0] r, g, b;
        input signed[COEF_W-1:0] c0, c1, c2;
        reg signed[PIXEL_W:0] r_p, g_p, b_p;
        reg signed[MAX_MULT_W-1:0] m0, m1, m2;
        reg signed[MAX_DIST_W-1:0] dist;
        reg signed[MAX_DIST_W:0] dist_rnd;
        reg signed[MAX_DIST_W:0] shifted;
        begin
            r_p = {1'b0, r};
            g_p = {1'b0, g};
            b_p = {1'b0, b};

            m0 = r_p * c0;
            m1 = g_p * c1;
            m2 = b_p * c2;

            dist = m0 + m1 + m2;
            dist_rnd = {dist[MAX_DIST_W-1], dist} + (1 << (FRAC_W - 1));
            shifted = dist_rnd >>> FRAC_W;

            if(dist_rnd[MAX_DIST_W])
                calc_expected = 0;

            else if(shifted > MAX_VAL)
                calc_expected = MAX_VAL;

            else
                calc_expected = shifted[PIXEL_W-1:0];
        end
    endfunction

    reg[PIXEL_W-1:0] exp_r [0:LINE_W*FRAME_W-1];
    reg[PIXEL_W-1:0] exp_g [0:LINE_W*FRAME_W-1];
    reg[PIXEL_W-1:0] exp_b [0:LINE_W*FRAME_W-1];

    integer wr_ptr = 0;
    integer rd_ptr = 0;
    integer err_count = 0;

    task send_pixel(input [PIXEL_W-1:0] r, input [PIXEL_W-1:0] g, input [PIXEL_W-1:0] b);
        begin
            valid_in <= 1;
            red_in   <= r;
            green_in <= g;
            blue_in  <= b;

            exp_r[wr_ptr] = calc_expected(r, g, b, c[0][0], c[0][1], c[0][2]);
            exp_g[wr_ptr] = calc_expected(r, g, b, c[1][0], c[1][1], c[1][2]);
            exp_b[wr_ptr] = calc_expected(r, g, b, c[2][0], c[2][1], c[2][2]);

            wr_ptr = wr_ptr + 1;
        end
    endtask

    integer i, j;
    reg[PIXEL_W-1:0] rand_red, rand_green, rand_blue;

    initial begin
        resetn   = 0;
        valid_in = 0;
        h_sync   = 0;
        v_sync   = 0;
        coef_in  = 0;
        red_in   = 0;
        green_in = 0;
        blue_in  = 0;

        repeat(2) @(posedge clk);
            resetn = 1;
        repeat(2) @(posedge clk);

            for(i = 0; i < FRAME_W; i = i + 1) begin
                for(j = 0; j < LINE_W; j = j + 1) begin
                    v_sync  = (i == 0 && j == 0);
                    h_sync  = (j == 0);
                    coef_in = (i == 0 && j == 0);

                    rand_red = $random & MAX_VAL;
                    rand_green = $random & MAX_VAL;
                    rand_blue = $random & MAX_VAL;

                    send_pixel(rand_red, rand_green, rand_blue);
                    @(posedge clk);
                end
            end

        valid_in = 0;
        repeat(20) @(posedge clk);

        if(err_count == 0)
            $display("SUCCESS: All %0d pixel comparisons passed!", rd_ptr);
        else
            $display("FAILED: Found %0d mismatch errors.", err_count);

        $finish;
    end

    always @(posedge clk) begin
        if(valid_out) begin
            if(red_out !== exp_r[rd_ptr] || green_out !== exp_g[rd_ptr] || blue_out !== exp_b[rd_ptr]) begin
                $display("ERROR at %0t | Pixel #%0d | Expected R:%0d G:%0d B:%0d | Got R:%0d G:%0d B:%0d",
                         $time, rd_ptr, exp_r[rd_ptr], exp_g[rd_ptr], exp_b[rd_ptr], red_out, green_out, blue_out);
                err_count = err_count + 1;
            end
            rd_ptr = rd_ptr + 1;
        end
    end

    initial begin
        $dumpfile("ccm_trace.vcd");
        $dumpvars(0, ccm_tb);
    end

endmodule

MODULES/CCM/RTL/ccm_trace.vcd
$date
	Thu Aug  6 09:37:46 2026
$end
$version
	Icarus Verilog
$end
$timescale
	1s
$end
$scope module ccm_tb $end
$var wire 1 ! valid_out $end
$var wire 1 " v_sync_out $end
$var wire 10 # red_out [9:0] $end
$var wire 1 $ h_sync_out $end
$var wire 10 % green_out [9:0] $end
$var wire 10 & blue_out [9:0] $end
$var parameter 32 ' COEF_W $end
$var parameter 32 ( FRAC_W $end
$var parameter 32 ) FRAME_W $end
$var parameter 32 * LINE_W $end
$var parameter 34 + MAX_DIST_W $end
$var parameter 33 , MAX_MULT_W $end
$var parameter 43 - MAX_VAL $end
$var parameter 32 . PIXEL_W $end
$var parameter 43 / SAT_LEVEL $end
$var reg 10 0 blue_in [9:0] $end
$var reg 1 1 clk $end
$var reg 1 2 coef_in $end
$var reg 10 3 green_in [9:0] $end
$var reg 1 4 h_sync $end
$var reg 10 5 rand_blue [9:0] $end
$var reg 10 6 rand_green [9:0] $end
$var reg 10 7 rand_red [9:0] $end
$var reg 10 8 red_in [9:0] $end
$var reg 1 9 resetn $end
$var reg 30 : row0 [29:0] $end
$var reg 30 ; row1 [29:0] $end
$var reg 30 < row2 [29:0] $end
$var reg 1 = v_sync $end
$var reg 1 > valid_in $end
$var integer 32 ? err_count [31:0] $end
$var integer 32 @ i [31:0] $end
$var integer 32 A j [31:0] $end
$var integer 32 B rd_ptr [31:0] $end
$var integer 32 C wr_ptr [31:0] $end
$scope function calc_expected $end
$var reg 10 D b [9:0] $end
$var reg 11 E b_p [10:0] $end
$var reg 10 F c0 [9:0] $end
$var reg 10 G c1 [9:0] $end
$var reg 10 H c2 [9:0] $end
$var reg 22 I dist [21:0] $end
$var reg 23 J dist_rnd [22:0] $end
$var reg 10 K g [9:0] $end
$var reg 11 L g_p [10:0] $end
$var reg 20 M m0 [19:0] $end
$var reg 20 N m1 [19:0] $end
$var reg 20 O m2 [19:0] $end
$var reg 10 P r [9:0] $end
$var reg 11 Q r_p [10:0] $end
$var reg 23 R shifted [22:0] $end
$upscope $end
$scope module dut $end
$var wire 10 S blue_in [9:0] $end
$var wire 1 1 clk $end
$var wire 1 2 coef_in $end
$var wire 10 T green_in [9:0] $end
$var wire 1 4 h_sync $end
$var wire 10 U red_in [9:0] $end
$var wire 1 9 resetn $end
$var wire 30 V row0 [29:0] $end
$var wire 30 W row1 [29:0] $end
$var wire 30 X row2 [29:0] $end
$var wire 1 = v_sync $end
$var wire 1 > valid_in $end
$var wire 23 Y red_dist_rnd [22:0] $end
$var wire 23 Z green_dist_rnd [22:0] $end
$var wire 23 [ blue_dist_rnd [22:0] $end
$var parameter 32 \ COEF_W $end
$var parameter 32 ] DELAY $end
$var parameter 32 ^ FRAC_W $end
$var parameter 32 _ FRAME_W $end
$var parameter 32 ` LINE_W $end
$var parameter 34 a MAX_DIST_W $end
$var parameter 33 b MAX_MULT_W $end
$var parameter 43 c MAX_VAL $end
$var parameter 32 d PIXEL_W $end
$var parameter 39 e ROUND_CONST $end
$var reg 22 f blue_dist [21:0] $end
$var reg 10 g blue_out [9:0] $end
$var reg 11 h blue_pipe [10:0] $end
$var reg 22 i green_dist [21:0] $end
$var reg 10 j green_out [9:0] $end
$var reg 11 k green_pipe [10:0] $end
$var reg 3 l h_pipe [2:0] $end
$var reg 1 $ h_sync_out $end
$var reg 22 m red_dist [21:0] $end
$var reg 10 n red_out [9:0] $end
$var reg 11 o red_pipe [10:0] $end
$var reg 3 p v_pipe [2:0] $end
$var reg 1 " v_sync_out $end
$var reg 1 ! valid_out $end
$var reg 3 q valid_pipe [2:0] $end
$var integer 32 r i [31:0] $end
$var integer 32 s j [31:0] $end
$upscope $end
$scope task send_pixel $end
$var reg 10 t b [9:0] $end
$var reg 10 u g [9:0] $end
$var reg 10 v r [9:0] $end
$upscope $end
$upscope $end
$enddefinitions $end
$comment Show the parameter values. $end
$dumpall
b10000000 e
b1010 d
b1111111111 c
b10100 b
b10110 a
b1000 `
b1000 _
b1000 ^
b11 ]
b1010 \
b1111111111 /
b1010 .
b1111111111 -
b10100 ,
b10110 +
b1000 *
b1000 )
b1000 (
b1010 '
$end
#0
$dumpvars
bx v
bx u
bx t
b11 s
b11 r
b0 q
b0 p
b0 o
b0 n
b0 m
b0 l
b0 k
b0 j
b0 i
b0 h
b0 g
b0 f
b10000000 [
b10000000 Z
b10000000 Y
b10011001111111001101111100110 X
b111110011001001100111111100110 W
b111110011011111001100100110011 V
b0 U
b0 T
b0 S
bx R
bx Q
bx P
bx O
bx N
bx M
bx L
bx K
bx J
bx I
bx H
bx G
bx F
bx E
bx D
b0 C
b0 B
bx A
bx @
b0 ?
0>
0=
b10011001111111001101111100110 <
b111110011001001100111111100110 ;
b111110011011111001100100110011 :
09
b0 8
bx 7
bx 6
bx 5
04
b0 3
02
01
b0 0
b0 &
b0 %
0$
b0 #
0"
0!
$end
#2
b11 s
b11 r
11
#4
01
#6
19
11
#8
01
#10
11
#12
01
#14
b1 p
b1 l
b1000001001 0
b1000001001 S
b1010000001 3
b1010000001 T
b100100100 8
b100100100 U
1>
b1 C
b1000010010 R
b100001001010001001 J
b100001001000001001 I
b100111000011001011 O
b11111011111011100110 N
b11111110001001011000 M
b1000001001 E
b1010000001 L
b100100100 Q
b100100100 P
b1010000001 K
b1000001001 D
b1111100110 F
b1111100110 G
b100110011 H
b1000001001 t
b1010000001 u
b100100100 v
b1000001001 5
b1010000001 6
b100100100 7
12
14
1=
b0 A
b0 @
11
#16
01
#18
b1000001001 h
b1010000001 k
b100100100 o
b10 p
b10 l
b1 q
b110001101 0
b110001101 S
b1100001101 3
b1100001101 T
b1001100011 8
b1001100011 U
b10 C
b1111100110 G
b101001111 R
b10100111100110111 J
b10100111010110111 I
b11101110000010111 O
b11111011000010101110 N
b11111100000111110010 M
b110001101 E
b1100001101 L
b1001100011 Q
b1001100011 P
b1100001101 K
b110001101 D
b1111100110 F
b100110011 H
b110001101 t
b1100001101 u
b1001100011 v
b110001101 5
b1100001101 6
b1001100011 7
02
04
0=
b1 A
11
#20
01
#22
b110001101 h
b1100001101 k
b1001100011 o
b100 p
b100 l
b11 q
b1100000001 0
b1100000001 S
b1000010010 3
b1000010010 T
b1100101 8
b1100101 U
b11 C
b1111100110 G
b1101011010 R
b110101101010011101 J
b110101101000011101 I
b111001101000110011 O
b11111100101000101100 N
b11111111010110111110 M
b1100000001 E
b1000010010 L
b1100101 Q
b1100101 P
b1000010010 K
b1100000001 D
b1111100110 F
b100110011 H
b1100000001 t
b1000010010 u
b1100101 v
b1100000001 5
b1000010010 6
b1100101 7
b10 A
11
#24
01
#26
b100001001010001001 [
b101010111010100001 Z
b1110100010101000 Y
b100001001000001001 f
b101010111000100001 i
b1110100000101000 m
b1100000001 h
b1000010010 k
b1100101 o
1"
1$
b0 p
b0 l
b111 q
b100111101 0
b100111101 S
b101110110 3
b101110110 T
b100001101 8
b100001101 U
b100 C
b1111100110 G
b100111011 R
b10011101101011001 J
b10011101011011001 I
b10111110000100111 O
b11111101101000000100 N
b11111110010010101110 M
b100111101 E
b101110110 L
b100001101 Q
b100001101 P
b101110110 K
b100111101 D
b1111100110 F
b100110011 H
b100111101 t
b101110110 u
b100001101 v
b100111101 5
b101110110 6
b100001101 7
b11 A
11
#28
01
#30
b10100111100110111 [
b110100001010110111 Z
b100110010110010101 Y
b1000010010 &
b1000010010 g
b1010101110 %
b1010101110 j
b11101000 #
b11101000 n
b10100111010110111 f
b110100001000110111 i
b100110010100010101 m
b100111101 h
b101110110 k
b100001101 o
0"
0$
1!
b111111001 0
b111111001 S
b1110001100 3
b1110001100 T
b1111101101 8
b1111101101 U
b101 C
b1111100110 G
b110011011 R
b11001101111010001 J
b11001101101010001 I
b100101110110011011 O
b11111010001111001000 N
b11111001100111101110 M
b111111001 E
b1110001100 L
b1111101101 Q
b1111101101 P
b1110001100 K
b111111001 D
b1111100110 F
b100110011 H
b111111001 t
b1110001100 u
b1111101101 v
b111111001 5
b1110001100 6
b1111101101 7
b100 A
11
#32
01
#34
b110101101010011101 [
b100010001110111010 Z
b11111111111010110110001 Y
b101001111 &
b101001111 g
b1101000010 %
b1101000010 j
b1001100101 #
b1001100101 n
b110101101000011101 f
b100010001100111010 i
b1111111111010100110001 m
b111111001 h
b1110001100 k
b1111101101 o
b1010101010 0
b1010101010 S
b11000101 3
b11000101 T
b11000110 8
b11000110 U
b110 C
b1111100110 G
b1100001010 R
b110000101001000000 J
b110000100111000000 I
b110011000111011110 O
b11111110101111111110 N
b11111110101111100100 M
b1010101010 E
b11000101 L
b11000110 Q
b11000110 P
b11000101 K
b1010101010 D
b1111100110 F
b100110011 H
b1 B
b1010101010 t
b11000101 u
b11000110 v
b1010101010 5
b11000101 6
b11000110 7
b101 A
11
#36
01
#38
b10011101101011001 [
b11000010101111110 Z
b1111110011101001 Y
b1101011010 &
b1101011010 g
b1000100011 %
b1000100011 j
b0 #
b0 n
b10011101011011001 f
b11000010011111110 i
b1111110001101001 m
b1010101010 h
b11000101 k
b11000110 o
b1000010010 0
b1000010010 S
b1001110111 3
b1001110111 T
b1111100101 8
b1111100101 U
b111 C
b1111100110 G
b111010110 R
b11101011010111110 J
b11101011000111110 I
b100111101110010110 O
b11111011111111101010 N
b11111001101010111110 M
b1000010010 E
b1001110111 L
b1111100101 Q
b1111100101 P
b1001110111 K
b1000010010 D
b1111100110 F
b100110011 H
b10 B
b1000010010 t
b1001110111 u
b1111100101 v
b1000010010 5
b1001110111 6
b1111100101 7
b110 A
11
#40
01
#42
b11001101111010001 [
b111010100000001000 Z
b1000010011000110101 Y
b100111011 &
b100111011 g
b110000101 %
b110000101 j
b11111100 #
b11111100 n
b11001101101010001 f
b111010011110001000 i
b1000010010110110101 m
b1000010010 h
b1001110111 k
b1111100101 o
b1011001110 0
b1011001110 S
b111110010 3
b111110010 T
b1110001111 8
b1110001111 U
b1000 C
b1111100110 G
b1011001110 R
b101100111001110000 J
b101100110111110000 I
b110101110100001010 O
b11111100110101101100 N
b11111010001101111010 M
b1011001110 E
b111110010 L
b1110001111 Q
b1110001111 P
b111110010 K
b1011001110 D
b1111100110 F
b100110011 H
b11 B
b1011001110 t
b111110010 u
b1110001111 v
b1011001110 5
b111110010 6
b1110001111 7
b111 A
11
#44
01
#46
b110000101001000000 [
b1001001101011111 Z
b1001010010101100 Y
b110011011 &
b110011011 g
b1110101000 %
b1110101000 j
b1111111111 #
b1111111111 n
b110000100111000000 f
b1001001011011111 i
b1001010000101100 m
b1011001110 h
b111110010 k
b1110001111 o
b1 l
b101011100 0
b101011100 S
b1011000101 3
b1011000101 T
b1011101000 8
b1011101000 U
b1001 C
b1111100110 G
b100001110 R
b10000111001000010 J
b10000110111000010 I
b11010000101010100 O
b11111011011111111110 N
b11111011010001110000 M
b101011100 E
b1011000101 L
b1011101000 Q
b1011101000 P
b1011000101 K
b101011100 D
b1111100110 F
b100110011 H
b100 B
b101011100 t
b1011000101 u
b1011101000 v
b101011100 5
b1011000101 6
b1011101000 7
14
b1 @
b0 A
11
#48
01
#50
b11101011010111110 [
b100101101000011111 Z
b1000011011000110101 Y
b1100001010 &
b1100001010 g
b10010011 %
b10010011 j
b10010100 #
b10010100 n
b11101011000111110 f
b100101100110011111 i
b1000011010110110101 m
b101011100 h
b1011000101 k
b1011101000 o
b10 l
b1001100101 0
b1001100101 S
b101101 3
b101101 T
b10111101 8
b10111101 U
b1010 C
b1111100110 G
b1011000111 R
b101100011111011011 J
b101100011101011011 I
b101101111100011111 O
b11111111101101101110 N
b11111110110011001110 M
b1001100101 E
b101101 L
b10111101 Q
b10111101 P
b101101 K
b1001100101 D
b1111100110 F
b100110011 H
b101 B
b1001100101 t
b101101 u
b10111101 v
b1001100101 5
b101101 6
b10111101 7
04
b1 A
11
#52
01
#54
b101100111001110000 [
b11011000001000100 Z
b111100100101111101 Y
b111010110 &
b111010110 g
b1001011010 %
b1001011010 j
b1111111111 #
b1111111111 n
b101100110111110000 f
b11010111111000100 i
b111100100011111101 m
b1001100101 h
b101101 k
b10111101 o
b100 l
b1010000000 0
b1010000000 S
b1100001010 3
b1100001010 T
b1001100011 8
b1001100011 U
b1011 C
b1111100110 G
b1001110010 R
b100111001011101110 J
b100111001001101110 I
b101111111110000000 O
b11111011000011111100 N
b11111100000111110010 M
b1010000000 E
b1100001010 L
b1001100011 Q
b1001100011 P
b1100001010 K
b1010000000 D
b1111100110 F
b100110011 H
b110 B
b1010000000 t
b1100001010 u
b1001100011 v
b1010000000 5
b1100001010 6
b1001100011 7
b10 A
11
#56
01
#58
b10000111001000010 [
b101110001111010111 Z
b110001000101011110 Y
b1011001110 &
b1011001110 g
b110110000 %
b110110000 j
b1111001001 #
b1111001001 n
b10000110111000010 f
b101110001101010111 i
b110001000011011110 m
b1010000000 h
b1100001010 k
b1001100011 o
1$
b0 l
b10011101 0
b10011101 S
b110101010 3
b110101010 T
b100100000 8
b100100000 U
b1100 C
b1111100110 G
b1110100 R
b111010001000011 J
b111001111000011 I
b1011110001000111 O
b11111101010010111100 N
b11111110001011000000 M
b10011101 E
b110101010 L
b100100000 Q
b100100000 P
b110101010 K
b10011101 D
b1111100110 F
b100110011 H
b111 B
b10011101 t
b110101010 u
b100100000 v
b10011101 5
b110101010 6
b100100000 7
b11 A
11
#60
01
#62
b101100011111011011 [
b11111111110010100000011 Z
b1010000001010011 Y
b100001110 &
b100001110 g
b1011100011 %
b1011100011 j
b1100010001 #
b1100010001 n
b101100011101011011 f
b1111111110010010000011 i
b1001111111010011 m
b10011101 h
b110101010 k
b100100000 o
0$
b1101 0
b1101 S
b10011 3
b10011 T
b1010010110 8
b1010010110 U
b1101 C
b1111100110 G
b11111111111111111001010 R
b11111111100101011101101 J
b1111111100101001101101 I
b111110010111 O
b11111111111000010010 N
b11111011110011000100 M
b1101 E
b10011 L
b1010010110 Q
b1010010110 P
b10011 K
b1101 D
b1111100110 F
b100110011 H
b1000 B
b1101 t
b10011 u
b1010010110 v
b1101 5
b10011 6
b1010010110 7
b100 A
11
#64
01
#66
b100111001011101110 [
b110010011001110000 Z
b100100110100110101 Y
b1011000111 &
b1011000111 g
b0 %
b0 j
b10100000 #
b10100000 n
b100111001001101110 f
b110010010111110000 i
b100100110010110101 m
b1101 h
b10011 k
b1010010110 o
b1011010101 0
b1011010101 S
b101101011 3
b101101011 T
b1001010011 8
b1001010011 U
b1110 C
b1111100110 G
b1100000100 R
b110000010010100011 J
b110000010000100011 I
b110110010101101111 O
b11111101101100100010 N
b11111100001110010010 M
b1011010101 E
b101101011 L
b1001010011 Q
b1001010011 P
b101101011 K
b1011010101 D
b1111100110 F
b100110011 H
b1001 B
b1011010101 t
b101101011 u
b1001010011 v
b1011010101 5
b101101011 6
b1001010011 7
b101 A
11
#68
01
#70
b111010001000011 [
b11101001000101100 Z
b10001111010101010 Y
b1001110010 &
b1001110010 g
b1100100110 %
b1100100110 j
b1001001101 #
b1001001101 n
b111001111000011 f
b11101000110101100 i
b10001111000101010 m
b1011010101 h
b101101011 k
b1001010011 o
b100011101 0
b100011101 S
b1010101110 3
b1010101110 T
b1000000010 8
b1000000010 U
b1111 C
b1111100110 G
b11011100 R
b1101110001100111 J
b1101101111100111 I
b10101010111000111 O
b11111011101001010100 N
b11111100101111001100 M
b100011101 E
b1010101110 L
b1000000010 Q
b1000000010 P
b1010101110 K
b100011101 D
b1111100110 F
b100110011 H
b1010 B
b100011101 t
b1010101110 u
b1000000010 v
b100011101 5
b1010101110 6
b1000000010 7
b110 A
11
#72
01
#74
b11111111100101011101101 [
b11111111101001010111011 Z
b110001011100100010 Y
b1110100 &
b1110100 g
b111010010 %
b111010010 j
b100011110 #
b100011110 n
b1111111100101001101101 f
b1111111101001000111011 i
b110001011010100010 m
b100011101 h
b1010101110 k
b1000000010 o
b100001010 0
b100001010 S
b100100011 3
b100100011 T
b1011001111 8
b1011001111 U
b10000 C
b1111100110 G
b11011000 R
b1101100011101010 J
b1101100001101010 I
b10011111011111110 O
b11111110001001110010 N
b11111011011011111010 M
b100001010 E
b100100011 L
b1011001111 Q
b1011001111 P
b100100011 K
b100001010 D
b1111100110 F
b100110011 H
b1011 B
b100001010 t
b100100011 u
b1011001111 v
b100001010 5
b100100011 6
b1011001111 7
b111 A
11
#76
01
#78
b110000010010100011 [
b10010110111000001 Z
b100101101110001001 Y
b0 &
b0 g
b0 %
b0 j
b1100010111 #
b1100010111 n
b110000010000100011 f
b10010110101000001 i
b100101101100001001 m
b100001010 h
b100100011 k
b1011001111 o
b1 l
b111110010 0
b111110010 S
b111100 3
b111100 T
b1011001010 8
b1011001010 U
b10001 C
b1111100110 G
b1000000111 R
b100000011100011010 J
b100000011010011010 I
b100101010100110110 O
b11111111100111101000 N
b11111011011101111100 M
b111110010 E
b111100 L
b1011001010 Q
b1011001010 P
b111100 K
b111110010 D
b1111100110 F
b100110011 H
b1100 B
b111110010 t
b111100 u
b1011001010 v
b111110010 5
b111100 6
b1011001010 7
14
b10 @
b0 A
11
#80
01
#82
b1101110001100111 [
b101110011000000100 Z
b100000011001001000 Y
b1100000100 &
b1100000100 g
b100101101 %
b100101101 j
b1001011011 #
b1001011011 n
b1101101111100111 f
b101110010110000100 i
b100000010111001000 m
b111110010 h
b111100 k
b1011001010 o
b10 l
b11011000 0
b11011000 S
b1101000001 3
b1101000001 T
b110001010 8
b110001010 U
b10010 C
b1111100110 G
b10000110 R
b1000011011101010 J
b1000011001101010 I
b10000001100001000 O
b11111010101101100110 N
b11111101011111111100 M
b11011000 E
b1101000001 L
b110001010 Q
b110001010 P
b1101000001 K
b11011000 D
b1111100110 F
b100110011 H
b1101 B
b11011000 t
b1101000001 u
b110001010 v
b11011000 5
b1101000001 6
b110001010 7
04
b1 A
11
#84
01
#86
b1101100011101010 [
b1111100101101111 Z
b110010011000101011 Y
b11011100 &
b11011100 g
b1011100110 %
b1011100110 j
b1000000110 #
b1000000110 n
b1101100001101010 f
b1111100011101111 i
b110010010110101011 m
b11011000 h
b1101000001 k
b110001010 o
b100 l
b111101011 0
b111101011 S
b1010001001 3
b1010001001 T
b1101111000 8
b1101111000 U
b10011 C
b1111100110 G
b110110001 R
b11011000100110111 J
b11011000010110111 I
b100100110011010001 O
b11111011111000010110 N
b11111010010111010000 M
b111101011 E
b1010001001 L
b1101111000 Q
b1101111000 P
b1010001001 K
b111101011 D
b1111100110 F
b100110011 H
b1110 B
b111101011 t
b1010001001 u
b1101111000 v
b111101011 5
b1010001001 6
b1101111000 7
b10 A
11
#88
01
#90
b100000011100011010 [
b11111111100110101011100 Z
b110010000000010010 Y
b11011000 &
b11011000 g
b11111001 %
b11111001 j
b1100100110 #
b1100100110 n
b100000011010011010 f
b1111111100110011011100 i
b110001111110010010 m
b111101011 h
b1010001001 k
b1101111000 o
1$
b0 l
b1110101110 0
b1110101110 S
b111000110 3
b111000110 T
b110110110 8
b110110110 U
b10100 C
b1111100110 G
b10000001111 R
b1000000111110010010 J
b1000000111100010010 I
b1000110100110101010 O
b11111101000111100100 N
b11111101001110000100 M
b1110101110 E
b111000110 L
b110110110 Q
b110110110 P
b111000110 K
b1110101110 D
b1111100110 F
b100110011 H
b1111 B
b1110101110 t
b111000110 u
b110110110 v
b1110101110 5
b111000110 6
b110110110 7
b11 A
11
#92
01
