MODULES/WBG/RTL/src/WBG.v
module WBG #(
    parameter PIXEL_W   = 10,
    parameter FRAME_W   = 1080,
    parameter LINE_W    = 2048,
    parameter FRAC_BITS = 8,
    parameter R_GAIN    = 384,
    parameter GR_GAIN   = 256,
    parameter GB_GAIN   = 256,
    parameter B_GAIN    = 512
)(
    input clk, resetn,
    input valid_in, v_sync, h_sync,
    input[PIXEL_W-1:0] pixel_in,
    output reg valid_out, v_sync_out, h_sync_out,
    output reg[PIXEL_W-1:0] pixel_out
);
    localparam MAX_VAL = {PIXEL_W{1'b1}};
    localparam DELAY   = 1;

    reg row, col;
    always @(posedge clk or negedge resetn) begin
        if(!resetn) begin
            row <= 0;
            col <= 0;
        end
        else begin
            if(v_sync) begin 
                row <= 0;
                col <= 0;
            end
            else if(h_sync) begin 
                col <= 0;
                row <= ~row;
            end
            else if(valid_in)
                col <= ~col;
        end
    end

    reg[DELAY-1:0] valid_pipe, h_pipe, v_pipe;
    reg[(PIXEL_W + FRAC_BITS + 4)-1:0] res_pipe;

    always @(posedge clk or negedge resetn) begin
        if(!resetn) begin
            pixel_out  <= 0;
            valid_out  <= 0;
            h_sync_out <= 0;
            v_sync_out <= 0;
            valid_pipe <= 0;
            v_pipe     <= 0;
            h_pipe     <= 0;
            res_pipe   <= 0;
        end
        else begin
            valid_pipe <= {valid_pipe[0], valid_in};
            h_pipe     <= {h_pipe[0], h_sync};
            v_pipe     <= {v_pipe[0], v_sync};

            valid_out  <= valid_pipe[DELAY-1];
            h_sync_out <= h_pipe[DELAY-1];
            v_sync_out <= v_pipe[DELAY-1];

            if(valid_in) begin
                case({row, col})
                    2'b00: res_pipe <= pixel_in * R_GAIN;
                    2'b01: res_pipe <= pixel_in * GR_GAIN;
                    2'b10: res_pipe <= pixel_in * GB_GAIN;
                    2'b11: res_pipe <= pixel_in * B_GAIN;
                endcase
            end

            if(valid_pipe[0]) begin
                if((res_pipe >> FRAC_BITS) > MAX_VAL) begin
                    pixel_out <= MAX_VAL;
                end
                else begin
                    pixel_out <= res_pipe[FRAC_BITS + PIXEL_W - 1 : FRAC_BITS];
                end
            end
        end
    end

endmodule

MODULES/WBG/RTL/src/wbg_tb.v
`timescale 1ns/1ps

module wbg_tb();
    localparam PIXEL_W   = 10;
    localparam FRAME_W   = 16;
    localparam LINE_W    = 16;
    localparam FRAC_BITS = 8;
    localparam R_GAIN    = 384;
    localparam GR_GAIN   = 256;
    localparam GB_GAIN   = 256;
    localparam B_GAIN    = 512;
    localparam MAX_VAL   = (1 << PIXEL_W) - 1;

    reg clk, resetn;
    reg valid_in, h_sync, v_sync;
    reg [PIXEL_W-1:0] pixel_in;
    
    wire valid_out, h_sync_out, v_sync_out;
    wire [PIXEL_W-1:0] pixel_out;

    WBG #(
        .PIXEL_W(PIXEL_W),
        .FRAME_W(FRAME_W),
        .LINE_W(LINE_W),
        .FRAC_BITS(FRAC_BITS),
        .R_GAIN(R_GAIN),
        .GR_GAIN(GR_GAIN),
        .GB_GAIN(GB_GAIN),
        .B_GAIN(B_GAIN)
    ) DUT (
        .clk(clk),
        .resetn(resetn),
        .valid_in(valid_in),
        .v_sync(v_sync),
        .h_sync(h_sync),
        .pixel_in(pixel_in),
        .valid_out(valid_out),
        .v_sync_out(v_sync_out),
        .h_sync_out(h_sync_out),
        .pixel_out(pixel_out)
    );

    initial clk = 0;
    always #1.5 clk = ~clk;
    
    reg [PIXEL_W-1:0] data;
    reg row, col;
    integer active_gain, exp;
    reg [PIXEL_W-1:0] exp_mem [0:1023]; 
    integer wr_ptr = 0;
    integer rd_ptr = 0;
    integer err_count = 0;

    task send_pixel;
        input [PIXEL_W-1:0] data;
        integer mult_val;
        begin
            pixel_in = data;
            valid_in = 1;
            
            row = DUT.row;
            col = DUT.col;

            case({row, col})
                2'b00: active_gain = R_GAIN;
                2'b01: active_gain = GR_GAIN;
                2'b10: active_gain = GB_GAIN;
                2'b11: active_gain = B_GAIN;
            endcase

            mult_val = data * active_gain;
            exp = mult_val >> FRAC_BITS;
            
            if (exp > MAX_VAL) begin
                exp = MAX_VAL;
            end
            
            exp_mem[wr_ptr] = exp;
            wr_ptr = wr_ptr + 1;
        end
    endtask

    integer i, j;
    initial begin
        resetn   = 0;
        pixel_in = 0; 
        valid_in = 0;
        h_sync   = 0; 
        v_sync   = 0;

        repeat(2) @(posedge clk);
        resetn = 1;
        repeat(2) @(posedge clk);
        
        for(i = 0; i < FRAME_W; i = i + 1) begin
            for(j = 0; j < LINE_W; j = j + 1) begin
                v_sync = (i == 0 && j == 0);
                h_sync = (j == 0);
                
                if(j % 10 == 0)      data = $urandom_range(0, 63);
                else if(j % 10 == 1) data = MAX_VAL;
                else                 data = $random & {PIXEL_W{1'b1}};
                
                send_pixel(data);
                @(posedge clk);
            end
        end
        valid_in = 0;
        repeat(10) @(posedge clk);

        if (err_count == 0) 
            $display("SUCCESS: All %0d checks passed!", rd_ptr);
        else 
            $display("FAILED: Found %0d errors.", err_count);

        $finish;
    end

    always @(posedge clk) begin
        if(valid_out) begin
            if(pixel_out !== exp_mem[rd_ptr]) begin
                $display("ERROR at %0t | Expected: %0d | Got: %0d", $time, exp_mem[rd_ptr], pixel_out);
                err_count = err_count + 1;
            end
            rd_ptr = rd_ptr + 1;
        end
    end
    
    initial begin
        $dumpfile("wbg_trace.vcd");
        $dumpvars(0, wbg_tb);
    end
endmodule

MODULES/WBG/RTL/wbg_trace.vcd
$date
	Mon Jul 13 10:30:10 2026
$end
$version
	Icarus Verilog
$end
$timescale
	1ps
$end
$scope module wbg_tb $end
$var wire 1 ! valid_out $end
$var wire 1 " v_sync_out $end
$var wire 10 # pixel_out [9:0] $end
$var wire 1 $ h_sync_out $end
$var parameter 32 % B_GAIN $end
$var parameter 32 & FRAC_BITS $end
$var parameter 32 ' FRAME_W $end
$var parameter 32 ( GB_GAIN $end
$var parameter 32 ) GR_GAIN $end
$var parameter 32 * LINE_W $end
$var parameter 43 + MAX_VAL $end
$var parameter 32 , PIXEL_W $end
$var parameter 32 - R_GAIN $end
$var reg 1 . clk $end
$var reg 1 / col $end
$var reg 10 0 data [9:0] $end
$var reg 1 1 h_sync $end
$var reg 10 2 pixel_in [9:0] $end
$var reg 1 3 resetn $end
$var reg 1 4 row $end
$var reg 1 5 v_sync $end
$var reg 1 6 valid_in $end
$var integer 32 7 active_gain [31:0] $end
$var integer 32 8 err_count [31:0] $end
$var integer 32 9 exp [31:0] $end
$var integer 32 : i [31:0] $end
$var integer 32 ; j [31:0] $end
$var integer 32 < rd_ptr [31:0] $end
$var integer 32 = wr_ptr [31:0] $end
$scope module DUT $end
$var wire 1 . clk $end
$var wire 1 1 h_sync $end
$var wire 10 > pixel_in [9:0] $end
$var wire 1 3 resetn $end
$var wire 1 5 v_sync $end
$var wire 1 6 valid_in $end
$var parameter 32 ? B_GAIN $end
$var parameter 32 @ DELAY $end
$var parameter 32 A FRAC_BITS $end
$var parameter 32 B FRAME_W $end
$var parameter 32 C GB_GAIN $end
$var parameter 32 D GR_GAIN $end
$var parameter 32 E LINE_W $end
$var parameter 10 F MAX_VAL $end
$var parameter 32 G PIXEL_W $end
$var parameter 32 H R_GAIN $end
$var reg 1 I col $end
$var reg 1 J h_pipe $end
$var reg 1 $ h_sync_out $end
$var reg 10 K pixel_out [9:0] $end
$var reg 22 L res_pipe [21:0] $end
$var reg 1 M row $end
$var reg 1 N v_pipe $end
$var reg 1 " v_sync_out $end
$var reg 1 ! valid_out $end
$var reg 1 O valid_pipe $end
$upscope $end
$scope task send_pixel $end
$var reg 10 P data [9:0] $end
$var integer 32 Q mult_val [31:0] $end
$upscope $end
$upscope $end
$enddefinitions $end
$comment Show the parameter values. $end
$dumpall
b110000000 H
b1010 G
b1111111111 F
b10000 E
b100000000 D
b100000000 C
b10000 B
b1000 A
b1 @
b1000000000 ?
b110000000 -
b1010 ,
b1111111111 +
b10000 *
b100000000 )
b100000000 (
b10000 '
b1000 &
b1000000000 %
$end
#0
$dumpvars
bx Q
bx P
0O
0N
0M
b0 L
b0 K
0J
0I
b0 >
b0 =
b0 <
bx ;
bx :
bx 9
b0 8
bx 7
06
05
x4
03
b0 2
01
bx 0
x/
0.
0$
b0 #
0"
0!
$end
#1500
1.
#3000
0.
#4500
13
1.
#6000
0.
#7500
1.
#9000
0.
#10500
b11011000000000 L
1N
1J
1O
b1 =
b110110 9
b11011000000000 Q
b110000000 7
0/
04
16
b100100 2
b100100 >
b100100 P
b100100 0
11
15
b0 ;
b0 :
1.
#12000
0.
#13500
b110110 #
b110110 K
b1011111111010000000 L
1"
1$
1!
0N
0J
1I
b10 =
b1111111111 9
b1011111111010000000 Q
b1111111111 2
b1111111111 >
b1111111111 P
b1111111111 0
01
05
b1 ;
1.
#15000
0.
#16500
0I
b1111111111 #
b1111111111 K
b10010010000000000 L
0"
0$
b11 =
b100100100 9
b10010010000000000 Q
b100000000 7
1/
b100100100 2
b100100100 >
b1 <
b100100100 P
b100100100 0
b10 ;
1.
#18000
0.
#19500
b100100100 #
b100100100 K
b111100000110000000 L
1I
b100 =
b1111000001 9
b111100000110000000 Q
b110000000 7
0/
b1010000001 2
b1010000001 >
b10 <
b1010000001 P
b1010000001 0
b11 ;
1.
#21000
0.
#22500
0I
b1111000001 #
b1111000001 K
b100000100100000000 L
b101 =
b1000001001 9
b100000100100000000 Q
b100000000 7
1/
b1000001001 2
b1000001001 >
b11 <
b1000001001 P
b1000001001 0
b100 ;
1.
#24000
0.
#25500
b1000001001 #
b1000001001 K
b111001010010000000 L
1I
b110 =
b1110010100 9
b111001010010000000 Q
b110000000 7
0/
b1001100011 2
b1001100011 >
b100 <
b1001100011 P
b1001100011 0
b101 ;
1.
#27000
0.
#28500
0I
b1110010100 #
b1110010100 K
b110000110100000000 L
b111 =
b1100001101 9
b110000110100000000 Q
b100000000 7
1/
b1100001101 2
b1100001101 >
b101 <
b1100001101 P
b1100001101 0
b110 ;
1.
#30000
0.
#31500
b1100001101 #
b1100001101 K
b100101001110000000 L
1I
b1000 =
b1001010011 9
b100101001110000000 Q
b110000000 7
0/
b110001101 2
b110001101 >
b110 <
b110001101 P
b110001101 0
b111 ;
1.
#33000
0.
#34500
0I
b1001010011 #
b1001010011 K
b110010100000000 L
b1001 =
b1100101 9
b110010100000000 Q
b100000000 7
1/
b1100101 2
b1100101 >
b111 <
b1100101 P
b1100101 0
b1000 ;
1.
#36000
0.
#37500
b1100101 #
b1100101 K
b110001101100000000 L
1I
b1010 =
b1100011011 9
b110001101100000000 Q
b110000000 7
0/
b1000010010 2
b1000010010 >
b1000 <
b1000010010 P
b1000010010 0
b1001 ;
1.
#39000
0.
#40500
0I
b1100011011 #
b1100011011 K
b1000000000000 L
b1011 =
b10000 9
b1000000000000 Q
b100000000 7
1/
b10000 2
b10000 >
b1001 <
b10000 P
b10000 0
b1010 ;
1.
#42000
0.
#43500
b10000 #
b10000 K
b1011111111010000000 L
1I
b1100 =
b1111111111 9
b1011111111010000000 Q
b110000000 7
0/
b1111111111 2
b1111111111 >
b1010 <
b1111111111 P
b1111111111 0
b1011 ;
1.
#45000
0.
#46500
0I
b1111111111 #
b1111111111 K
b110000000100000000 L
b1101 =
b1100000001 9
b110000000100000000 Q
b100000000 7
1/
b1100000001 2
b1100000001 >
b1011 <
b1100000001 P
b1100000001 0
b1100 ;
1.
#48000
0.
#49500
b1100000001 #
b1100000001 K
b11001001110000000 L
1I
b1110 =
b110010011 9
b11001001110000000 Q
b110000000 7
0/
b100001101 2
b100001101 >
b1100 <
b100001101 P
b100001101 0
b1101 ;
1.
#51000
0.
#52500
0I
b110010011 #
b110010011 K
b10111011000000000 L
b1111 =
b101110110 9
b10111011000000000 Q
b100000000 7
1/
b101110110 2
b101110110 >
b1101 <
b101110110 P
b101110110 0
b1110 ;
1.
#54000
0.
#55500
b101110110 #
b101110110 K
b11101101110000000 L
1I
b10000 =
b111011011 9
b11101101110000000 Q
b110000000 7
0/
b100111101 2
b100111101 >
b1110 <
b100111101 P
b100111101 0
b1111 ;
1.
#57000
0.
#58500
1M
0I
b111011011 #
b111011011 K
b100000000 L
1J
b10001 =
b1 9
b100000000 Q
b100000000 7
1/
b1 2
b1 >
b1111 <
b1 P
b1 0
11
b1 :
b0 ;
1.
#60000
0.
#61500
b1 #
b1 K
b111111111100000000 L
1$
0J
1I
b10010 =
b1111111111 9
b111111111100000000 Q
0/
14
b1111111111 2
b1111111111 >
b10000 <
b1111111111 P
b1111111111 0
01
b1 ;
1.
#63000
0.
#64500
0I
b1111111111 #
b1111111111 K
b1111101101000000000 L
0$
b10011 =
b1111111111 9
b1111101101000000000 Q
b1000000000 7
1/
b1111101101 2
b1111101101 >
b10001 <
b1111101101 P
b1111101101 0
b10 ;
1.
#66000
0.
#67500
b111000110000000000 L
1I
b10100 =
b1110001100 9
b111000110000000000 Q
b100000000 7
0/
b1110001100 2
b1110001100 >
b10010 <
b1110001100 P
b1110001100 0
b11 ;
1.
#69000
0.
#70500
0I
b1110001100 #
b1110001100 K
b111111001000000000 L
b10101 =
b1111110010 9
b111111001000000000 Q
b1000000000 7
1/
b111111001 2
b111111001 >
b10011 <
b111111001 P
b111111001 0
b100 ;
1.
#72000
0.
#73500
b1111110010 #
b1111110010 K
b1100011000000000 L
1I
b10110 =
b11000110 9
b1100011000000000 Q
b100000000 7
0/
b11000110 2
b11000110 >
b10100 <
b11000110 P
b11000110 0
b101 ;
1.
#75000
0.
#76500
0I
b11000110 #
b11000110 K
b11000101000000000 L
b10111 =
b110001010 9
b11000101000000000 Q
b1000000000 7
1/
b11000101 2
b11000101 >
b10101 <
b11000101 P
b11000101 0
b110 ;
1.
#78000
0.
#79500
b110001010 #
b110001010 K
b101010101000000000 L
1I
b11000 =
b1010101010 9
b101010101000000000 Q
b100000000 7
0/
b1010101010 2
b1010101010 >
b10110 <
b1010101010 P
b1010101010 0
b111 ;
1.
#81000
0.
#82500
0I
b1010101010 #
b1010101010 K
b1111100101000000000 L
b11001 =
b1111111111 9
b1111100101000000000 Q
b1000000000 7
1/
b1111100101 2
b1111100101 >
b10111 <
b1111100101 P
b1111100101 0
b1000 ;
1.
#84000
0.
#85500
b1111111111 #
b1111111111 K
b100111011100000000 L
1I
b11010 =
b1001110111 9
b100111011100000000 Q
b100000000 7
0/
b1001110111 2
b1001110111 >
b11000 <
b1001110111 P
b1001110111 0
b1001 ;
1.
#87000
0.
#88500
0I
b1001110111 #
b1001110111 K
b1100000000000 L
b11011 =
b11000 9
b1100000000000 Q
b1000000000 7
1/
b1100 2
b1100 >
b11001 <
b1100 P
b1100 0
b1010 ;
1.
#90000
0.
#91500
b11000 #
b11000 K
b111111111100000000 L
1I
b11100 =
b1111111111 9
b111111111100000000 Q
b100000000 7
0/
b1111111111 2
b1111111111 >
b11010 <
b1111111111 P
b1111111111 0
b1011 ;
1.
#93000
0.
#94500
0I
b1111111111 #
b1111111111 K
b1000010010000000000 L
b11101 =
b1111111111 9
b1000010010000000000 Q
b1000000000 7
1/
b1000010010 2
b1000010010 >
b11011 <
b1000010010 P
b1000010010 0
b1100 ;
1.
#96000
0.
#97500
b111000111100000000 L
1I
b11110 =
b1110001111 9
b111000111100000000 Q
b100000000 7
0/
b1110001111 2
b1110001111 >
b11100 <
b1110001111 P
b1110001111 0
b1101 ;
1.
#99000
0.
#100500
0I
b1110001111 #
b1110001111 K
b111110010000000000 L
b11111 =
b1111100100 9
b111110010000000000 Q
b1000000000 7
1/
b111110010 2
b111110010 >
b11101 <
b111110010 P
b111110010 0
b1110 ;
1.
#102000
0.
#103500
b1111100100 #
b1111100100 K
b101100111000000000 L
1I
b100000 =
b1011001110 9
b101100111000000000 Q
b100000000 7
0/
b1011001110 2
b1011001110 >
b11110 <
b1011001110 P
b1011001110 0
b1111 ;
1.
#105000
0.
#106500
0M
0I
b1011001110 #
b1011001110 K
b100001000000000 L
1J
b100001 =
b1000010 9
b100001000000000 Q
b1000000000 7
1/
b100001 2
b100001 >
b11111 <
b100001 P
b100001 0
11
b10 :
b0 ;
1.
#108000
0.
#109500
b1000010 #
b1000010 K
b1011111111010000000 L
1$
0J
1I
b100010 =
b1111111111 9
b1011111111010000000 Q
b110000000 7
0/
04
b1111111111 2
b1111111111 >
b100000 <
b1111111111 P
b1111111111 0
01
b1 ;
1.
#111000
0.
#112500
0I
b1111111111 #
b1111111111 K
b101110100000000000 L
0$
b100011 =
b1011101000 9
b101110100000000000 Q
b100000000 7
1/
b1011101000 2
b1011101000 >
b100001 <
b1011101000 P
b1011101000 0
b10 ;
1.
#114000
0.
#115500
b1011101000 #
b1011101000 K
b1000010011110000000 L
1I
b100100 =
b1111111111 9
b1000010011110000000 Q
b110000000 7
0/
b1011000101 2
b1011000101 >
b100010 <
b1011000101 P
b1011000101 0
b11 ;
1.
#117000
0.
#118500
0I
b1111111111 #
b1111111111 K
b10101110000000000 L
b100101 =
b101011100 9
b10101110000000000 Q
b100000000 7
1/
b101011100 2
b101011100 >
b100011 <
b101011100 P
b101011100 0
b100 ;
1.
#120000
0.
#121500
b101011100 #
b101011100 K
b10001101110000000 L
1I
b100110 =
b100011011 9
b10001101110000000 Q
b110000000 7
0/
b10111101 2
b10111101 >
b100100 <
b10111101 P
b10111101 0
b101 ;
1.
#123000
0.
#124500
0I
b100011011 #
b100011011 K
b10110100000000 L
b100111 =
b101101 9
b10110100000000 Q
b100000000 7
1/
b101101 2
b101101 >
b100101 <
b101101 P
b101101 0
b110 ;
1.
#126000
0.
#127500
b101101 #
b101101 K
b111001011110000000 L
1I
b101000 =
b1110010111 9
b111001011110000000 Q
b110000000 7
0/
b1001100101 2
b1001100101 >
b100110 <
b1001100101 P
b1001100101 0
b111 ;
1.
#129000
0.
#130500
0I
b1110010111 #
b1110010111 K
b100110001100000000 L
b101001 =
b1001100011 9
b100110001100000000 Q
b100000000 7
1/
b1001100011 2
b1001100011 >
b100111 <
b1001100011 P
b1001100011 0
b1000 ;
1.
#132000
0.
#133500
b1001100011 #
b1001100011 K
b1001000111100000000 L
1I
b101010 =
b1111111111 9
b1001000111100000000 Q
b110000000 7
0/
b1100001010 2
b1100001010 >
b101000 <
b1100001010 P
b1100001010 0
b1001 ;
1.
#135000
0.
#136500
0I
b1111111111 #
b1111111111 K
b11000100000000 L
b101011 =
b110001 9
b11000100000000 Q
b100000000 7
1/
b110001 2
b110001 >
b101001 <
b110001 P
b110001 0
b1010 ;
1.
#138000
0.
#139500
b110001 #
b110001 K
b1011111111010000000 L
1I
b101100 =
b1111111111 9
b1011111111010000000 Q
b110000000 7
0/
b1111111111 2
b1111111111 >
b101010 <
b1111111111 P
b1111111111 0
b1011 ;
1.
#141000
0.
#142500
0I
b1111111111 #
b1111111111 K
b101000000000000000 L
b101101 =
b1010000000 9
b101000000000000000 Q
b100000000 7
1/
b1010000000 2
b1010000000 >
b101011 <
b1010000000 P
b1010000000 0
b1100 ;
1.
#144000
0.
#145500
b1010000000 #
b1010000000 K
b11011000000000000 L
1I
b101110 =
b110110000 9
b11011000000000000 Q
b110000000 7
0/
b100100000 2
b100100000 >
b101100 <
b100100000 P
b100100000 0
b1101 ;
1.
#147000
0.
#148500
0I
b110110000 #
b110110000 K
b11010101000000000 L
b101111 =
b110101010 9
b11010101000000000 Q
b100000000 7
1/
b110101010 2
b110101010 >
b101101 <
b110101010 P
b110101010 0
b1110 ;
1.
#150000
0.
#151500
b110101010 #
b110101010 K
b1110101110000000 L
1I
b110000 =
b11101011 9
b1110101110000000 Q
b110000000 7
0/
b10011101 2
b10011101 >
b101110 <
b10011101 P
b10011101 0
b1111 ;
1.
#153000
0.
#154500
1M
0I
b11101011 #
b11101011 K
b110000000000 L
1J
b110001 =
b1100 9
b110000000000 Q
b100000000 7
1/
b1100 2
b1100 >
b101111 <
b1100 P
b1100 0
11
b11 :
b0 ;
1.
#156000
0.
#157500
b1100 #
b1100 K
b111111111100000000 L
1$
0J
1I
b110010 =
b1111111111 9
b111111111100000000 Q
0/
14
b1111111111 2
b1111111111 >
b110000 <
b1111111111 P
b1111111111 0
01
b1 ;
1.
#159000
0.
#160500
0I
b1111111111 #
b1111111111 K
b1010010110000000000 L
0$
b110011 =
b1111111111 9
b1010010110000000000 Q
b1000000000 7
1/
b1010010110 2
b1010010110 >
b110001 <
b1010010110 P
b1010010110 0
b10 ;
1.
#162000
0.
#163500
b1001100000000 L
1I
b110100 =
b10011 9
b1001100000000 Q
b100000000 7
0/
b10011 2
b10011 >
b110010 <
b10011 P
b10011 0
b11 ;
1.
#165000
0.
#166500
0I
b10011 #
b10011 K
b1101000000000 L
b110101 =
b11010 9
b1101000000000 Q
b1000000000 7
1/
b1101 2
b1101 >
b110011 <
b1101 P
b1101 0
b100 ;
1.
#168000
0.
#169500
b11010 #
b11010 K
b100101001100000000 L
1I
b110110 =
b1001010011 9
b100101001100000000 Q
b100000000 7
0/
b1001010011 2
b1001010011 >
b110100 <
b1001010011 P
b1001010011 0
b101 ;
1.
#171000
0.
#172500
0I
b1001010011 #
b1001010011 K
b101101011000000000 L
b110111 =
b1011010110 9
b101101011000000000 Q
b1000000000 7
1/
b101101011 2
b101101011 >
b110101 <
b101101011 P
b101101011 0
b110 ;
1.
#174000
0.
#175500
b1011010110 #
b1011010110 K
b101101010100000000 L
1I
b111000 =
b1011010101 9
b101101010100000000 Q
b100000000 7
0/
b1011010101 2
b1011010101 >
b110110 <
b1011010101 P
b1011010101 0
b111 ;
1.
#177000
0.
#178500
0I
b1011010101 #
b1011010101 K
b1000000010000000000 L
b111001 =
b1111111111 9
b1000000010000000000 Q
b1000000000 7
1/
b1000000010 2
b1000000010 >
b110111 <
b1000000010 P
b1000000010 0
b1000 ;
1.
#180000
0.
#181500
b1111111111 #
b1111111111 K
b101010111000000000 L
1I
b111010 =
b1010101110 9
b101010111000000000 Q
b100000000 7
0/
b1010101110 2
b1010101110 >
b111000 <
b1010101110 P
b1010101110 0
b1001 ;
1.
#183000
0.
#184500
0I
b1010101110 #
b1010101110 K
b10000000000 L
b111011 =
b100 9
b10000000000 Q
b1000000000 7
1/
b10 2
b10 >
b111001 <
b10 P
b10 0
b1010 ;
1.
#186000
0.
#187500
b100 #
b100 K
b111111111100000000 L
1I
b111100 =
b1111111111 9
b111111111100000000 Q
b100000000 7
0/
b1111111111 2
b1111111111 >
b111010 <
b1111111111 P
b1111111111 0
b1011 ;
1.
#189000
0.
#190500
0I
b1111111111 #
b1111111111 K
b100011101000000000 L
b111101 =
b1000111010 9
b100011101000000000 Q
b1000000000 7
1/
b100011101 2
b100011101 >
b111011 <
b100011101 P
b100011101 0
b1100 ;
1.
#192000
0.
#193500
b1000111010 #
b1000111010 K
b101100111100000000 L
1I
b111110 =
b1011001111 9
b101100111100000000 Q
b100000000 7
0/
b1011001111 2
b1011001111 >
b111100 <
b1011001111 P
b1011001111 0
b1101 ;
1.
#195000
0.
#196500
0I
b1011001111 #
b1011001111 K
b100100011000000000 L
b111111 =
b1001000110 9
b100100011000000000 Q
b1000000000 7
1/
b100100011 2
b100100011 >
b111101 <
b100100011 P
b100100011 0
b1110 ;
1.
#198000
0.
#199500
b1001000110 #
b1001000110 K
b10000101000000000 L
1I
b1000000 =
b100001010 9
b10000101000000000 Q
b100000000 7
0/
b100001010 2
b100001010 >
b111110 <
b100001010 P
b100001010 0
b1111 ;
1.
#201000
0.
#202500
0M
0I
b100001010 #
b100001010 K
b100000000000000 L
1J
b1000001 =
b1000000 9
b100000000000000 Q
b1000000000 7
1/
b100000 2
b100000 >
b111111 <
b100000 P
b100000 0
11
b100 :
b0 ;
1.
#204000
0.
#205500
b1000000 #
b1000000 K
b1011111111010000000 L
1$
0J
1I
b1000010 =
b1111111111 9
b1011111111010000000 Q
b110000000 7
0/
04
b1111111111 2
b1111111111 >
b1000000 <
b1111111111 P
b1111111111 0
01
b1 ;
1.
#207000
0.
#208500
0I
b1111111111 #
b1111111111 K
b101100101000000000 L
0$
b1000011 =
b1011001010 9
b101100101000000000 Q
b100000000 7
1/
b1011001010 2
b1011001010 >
b1000001 <
b1011001010 P
b1011001010 0
b10 ;
1.
#210000
0.
#211500
b1011001010 #
b1011001010 K
b101101000000000 L
1I
b1000100 =
b1011010 9
b101101000000000 Q
b110000000 7
0/
b111100 2
b111100 >
b1000010 <
b111100 P
b111100 0
b11 ;
1.
#213000
0.
#214500
0I
b1011010 #
b1011010 K
b11111001000000000 L
b1000101 =
b111110010 9
b11111001000000000 Q
b100000000 7
1/
b111110010 2
b111110010 >
b1000011 <
b111110010 P
b111110010 0
b100 ;
1.
#216000
0.
#217500
b111110010 #
b111110010 K
b100100111100000000 L
1I
b1000110 =
b1001001111 9
b100100111100000000 Q
b110000000 7
0/
b110001010 2
b110001010 >
b1000100 <
b110001010 P
b110001010 0
b101 ;
1.
#219000
0.
#220500
0I
b1001001111 #
b1001001111 K
b110100000100000000 L
b1000111 =
b1101000001 9
b110100000100000000 Q
b100000000 7
1/
b1101000001 2
b1101000001 >
b1000101 <
b1101000001 P
b1101000001 0
b110 ;
1.
#222000
0.
#223500
b1101000001 #
b1101000001 K
b10100010000000000 L
1I
b1001000 =
b101000100 9
b10100010000000000 Q
b110000000 7
0/
b11011000 2
b11011000 >
b1000110 <
b11011000 P
b11011000 0
b111 ;
1.
#225000
0.
#226500
0I
b101000100 #
b101000100 K
b110111100000000000 L
b1001001 =
b1101111000 9
b110111100000000000 Q
b100000000 7
1/
b1101111000 2
b1101111000 >
b1000111 <
b1101111000 P
b1101111000 0
b1000 ;
1.
#228000
0.
#229500
b1101111000 #
b1101111000 K
b111100110110000000 L
1I
b1001010 =
b1111001101 9
b111100110110000000 Q
b110000000 7
0/
b1010001001 2
b1010001001 >
b1001000 <
b1010001001 P
b1010001001 0
b1001 ;
1.
#231000
0.
#232500
0I
b1111001101 #
b1111001101 K
b10000100000000 L
b1001011 =
b100001 9
b10000100000000 Q
b100000000 7
1/
b100001 2
b100001 >
b1001001 <
b100001 P
b100001 0
b1010 ;
1.
#234000
0.
#235500
b100001 #
b100001 K
b1011111111010000000 L
1I
b1001100 =
b1111111111 9
b1011111111010000000 Q
b110000000 7
0/
b1111111111 2
b1111111111 >
b1001010 <
b1111111111 P
b1111111111 0
b1011 ;
1.
#237000
0.
#238500
0I
b1111111111 #
b1111111111 K
b11110101100000000 L
b1001101 =
b111101011 9
b11110101100000000 Q
b100000000 7
1/
b111101011 2
b111101011 >
b1001011 <
b111101011 P
b111101011 0
b1100 ;
1.
#240000
0.
#241500
b111101011 #
b111101011 K
b101001000100000000 L
1I
b1001110 =
b1010010001 9
b101001000100000000 Q
b110000000 7
0/
b110110110 2
b110110110 >
b1001100 <
b110110110 P
b110110110 0
b1101 ;
1.
#243000
0.
#244500
0I
b1010010001 #
b1010010001 K
b11100011000000000 L
b1001111 =
b111000110 9
b11100011000000000 Q
b100000000 7
1/
b111000110 2
b111000110 >
b1001101 <
b111000110 P
b111000110 0
b1110 ;
1.
#246000
0.
#247500
b111000110 #
b111000110 K
b1011000010100000000 L
1I
b1010000 =
b1111111111 9
b1011000010100000000 Q
b110000000 7
0/
b1110101110 2
b1110101110 >
b1001110 <
b1110101110 P
b1110101110 0
b1111 ;
1.
#249000
0.
#250500
1M
0I
b1111111111 #
b1111111111 K
b10111000000000 L
1J
b1010001 =
b101110 9
b10111000000000 Q
b100000000 7
1/
b101110 2
b101110 >
b1001111 <
b101110 P
b101110 0
11
b101 :
b0 ;
1.
#252000
0.
#253500
b101110 #
b101110 K
b111111111100000000 L
1$
0J
1I
b1010010 =
b1111111111 9
b111111111100000000 Q
0/
14
b1111111111 2
b1111111111 >
b1010000 <
b1111111111 P
b1111111111 0
01
b1 ;
1.
#255000
0.
#256500
0I
b1111111111 #
b1111111111 K
b1010111100000000000 L
0$
b1010011 =
b1111111111 9
b1010111100000000000 Q
b1000000000 7
1/
b1010111100 2
b1010111100 >
b1010001 <
b1010111100 P
b1010111100 0
b10 ;
1.
#258000
0.
#259500
b10010101000000000 L
1I
b1010100 =
b100101010 9
b10010101000000000 Q
b100000000 7
0/
b100101010 2
b100101010 >
b1010010 <
b100101010 P
b100101010 0
b11 ;
1.
#261000
0.
#262500
0I
b100101010 #
b100101010 K
b1000001011000000000 L
b1010101 =
b1111111111 9
b1000001011000000000 Q
b1000000000 7
1/
b1000001011 2
b1000001011 >
b1010011 <
b1000001011 P
b1000001011 0
b100 ;
1.
#264000
0.
#265500
b1111111111 #
b1111111111 K
b100111000100000000 L
1I
b1010110 =
b1001110001 9
b100111000100000000 Q
b100000000 7
0/
b1001110001 2
b1001110001 >
b1010100 <
b1001110001 P
b1001110001 0
b101 ;
1.
#267000
0.
#268500
0I
b1001110001 #
b1001110001 K
b110000101000000000 L
b1010111 =
b1100001010 9
b110000101000000000 Q
b1000000000 7
1/
b110000101 2
b110000101 >
b1010101 <
b110000101 P
b110000101 0
b110 ;
1.
#270000
0.
#271500
b1100001010 #
b1100001010 K
b10100111100000000 L
1I
b1011000 =
b101001111 9
b10100111100000000 Q
b100000000 7
0/
b101001111 2
b101001111 >
b1010110 <
b101001111 P
b101001111 0
b111 ;
1.
#273000
0.
#274500
0I
b101001111 #
b101001111 K
b111011000000000 L
b1011001 =
b1110110 9
b111011000000000 Q
b1000000000 7
1/
b111011 2
b111011 >
b1010111 <
b111011 P
b111011 0
b1000 ;
1.
#276000
0.
#277500
b1110110 #
b1110110 K
b110011101000000000 L
1I
b1011010 =
b1100111010 9
b110011101000000000 Q
b100000000 7
0/
b1100111010 2
b1100111010 >
b1011000 <
b1100111010 P
b1100111010 0
b1001 ;
1.
#279000
0.
