MODULES/LSC/RTL/src/LSC.v
// Lens Shading Correction with simplified radial equation
// pixel_out = pixel_in * Gain
// Gain = 1 + c2 * R^2 + c4 * R^4 .... (ommitted past c2)
// R^2 = dx^2 + dy^2
// find dx, dy -> find R^2 -> find Gain -> Multipler -> output
// Follows RGGB raw bayer
module LSC #(
    parameter PIXEL_W = 10,
    parameter LINE_W  = 2048,
    parameter FRAME_W = 1080,
    parameter C2_R    = 2, 
    parameter C2_Gr   = 2,
    parameter C2_Gb   = 2,
    parameter C2_B    = 2
)(
    input clk, resetn,
    input valid_in, h_sync, v_sync,
    input[PIXEL_W-1:0] pixel_in,
    output reg valid_out, h_sync_out, v_sync_out,
    output reg[PIXEL_W-1:0] pixel_out
);
    localparam MAX_VAL = {PIXEL_W{1'b1}};
    localparam DELAY   = 6;

    localparam LINE_CNT  = $clog2(LINE_W);
    localparam FRAME_CNT = $clog2(FRAME_W);
    
    localparam MID_X = LINE_W/2;
    localparam MID_Y = FRAME_W/2;

    localparam DX_W = $clog2(MID_X+1);                             
    localparam DY_W = $clog2(MID_Y+1);
    localparam X2_W = $clog2((MID_X**2)) + 1;
    localparam Y2_W = $clog2((MID_Y**2)) + 1;
    localparam R2_W = $clog2((MID_X**2) + (MID_Y**2)) + 1;

    localparam FP_SHIFT = 24; 
    localparam GAIN_W   = R2_W + FP_SHIFT;

    reg[LINE_CNT-1:0]  x_count;
    reg[FRAME_CNT-1:0] y_count;

    always@(posedge clk or negedge resetn) begin
        if(!resetn) begin
            x_count <= {LINE_CNT{1'b0}};
            y_count <= {FRAME_CNT{1'b0}};
        end 
        else if(v_sync) begin
            x_count <= {LINE_CNT{1'b0}};
            y_count <= {FRAME_CNT{1'b0}};
        end 
        else if(valid_in) begin
            if(x_count == LINE_W - 1) begin
                x_count <= {LINE_CNT{1'b0}};
                y_count <= y_count + 1'b1;
            end 
            else begin
                x_count <= x_count + 1'b1;
            end
        end
    end
  
    reg[DELAY-1:0]   valid_pipe;
    reg[DELAY-1:0]   hsync_pipe;
    reg[DELAY-1:0]   vsync_pipe;
    reg[PIXEL_W-1:0] pixel_pipe [DELAY-1:0];

    reg[DX_W-1:0] x_dist;
    reg[DY_W-1:0] y_dist;
    reg[R2_W-1:0] r2;
    reg[X2_W-1:0] x2;
    reg[Y2_W-1:0] y2;

    reg[GAIN_W-1:0] gain;
    reg[1:0] coef_pipe [DELAY-2:0];

    reg[R2_W: 0] r2_R , r2_Gr, r2_Gb, r2_B;

    reg[GAIN_W+PIXEL_W-1:0] product;
  
    wire[GAIN_W+PIXEL_W-1:0] shifted = product >> FP_SHIFT;
    wire[PIXEL_W-1:0] clamped_pixel  = (shifted > MAX_VAL) ? {PIXEL_W{1'b1}} : shifted[PIXEL_W-1:0];

    integer i;
    
    always@(posedge clk or negedge resetn) begin
        if(!resetn) begin
            pixel_out  <= {PIXEL_W{1'b0}};
            valid_out  <= 1'b0;
            h_sync_out <= 1'b0;
            v_sync_out <= 1'b0;
            valid_pipe <= {DELAY{1'b0}};
            hsync_pipe <= {DELAY{1'b0}};
            vsync_pipe <= {DELAY{1'b0}};
            x_dist     <= {DX_W{1'b0}};
            y_dist     <= {DY_W{1'b0}};
            r2         <= {R2_W{1'b0}};
            gain       <= {GAIN_W{1'b0}};

            for(i = 0; i < DELAY; i = i + 1) 
                pixel_pipe[i] <= {PIXEL_W{1'b0}};
            
            for(i = 0; i < DELAY-1; i = i + 1) 
                coef_pipe[i] <= 2'b0;
        end 
        else begin
            valid_pipe <= {valid_pipe[DELAY-2:0], valid_in};
            hsync_pipe <= {hsync_pipe[DELAY-2:0], h_sync};
            vsync_pipe <= {vsync_pipe[DELAY-2:0], v_sync};

            valid_out  <= valid_pipe[DELAY-1];
            h_sync_out <= hsync_pipe[DELAY-1];
            v_sync_out <= vsync_pipe[DELAY-1];

            for(i = DELAY-1; i > 0; i = i - 1) 
                pixel_pipe[i] <= pixel_pipe[i-1];
            pixel_pipe[0] <= pixel_in;

            for(i = DELAY-2; i > 0; i = i - 1) 
                coef_pipe[i] <= coef_pipe[i-1];
            coef_pipe[0] <= {y_count[0], x_count[0]}; 

            if(valid_in) begin
                x_dist <= (x_count <= MID_X) ? (MID_X - x_count) : (x_count - MID_X);
                y_dist <= (y_count <= MID_Y) ? (MID_Y - y_count) : (y_count - MID_Y);
            end

            if(valid_pipe[0]) begin
                x2 <= (x_dist * x_dist);
                y2 <= (y_dist * y_dist);
            end

            if(valid_pipe[1]) begin
                r2 <= x2 + y2;
            end

            if( valid_pipe[2] ) begin
                r2_R  <= C2_R  * r2; 
                r2_Gr <= C2_Gr * r2;
                r2_Gb <= C2_Gb * r2;
                r2_B  <= C2_B  * r2;
            end

            if(valid_pipe[3]) begin
                case(coef_pipe[DELAY-2])
                    2'b00: gain <= (1 << FP_SHIFT) + r2_R ;
                    2'b01: gain <= (1 << FP_SHIFT) + r2_Gr;
                    2'b10: gain <= (1 << FP_SHIFT) + r2_Gb;
                    2'b11: gain <= (1 << FP_SHIFT) + r2_B ;
                endcase
            end

            if(valid_pipe[4]) begin
                product <= gain * pixel_pipe[DELAY-2];
            end

            if(valid_pipe[5]) begin
                pixel_out  <= clamped_pixel;
            end
        end
    end
endmodule

MODULES/LSC/RTL/src/lsc_tb.v
`timescale 1ns/1ps
module lsc_tb();
    localparam PIXEL_W = 10;
    localparam LINE_W  = 1024;
    localparam FRAME_W = 4;
    localparam C2_R    = 2; 
    localparam C2_Gr   = 2;
    localparam C2_Gb   = 2;
    localparam C2_B    = 2;

    reg clk, resetn;
    reg valid_in, h_sync, v_sync;
    reg[PIXEL_W-1:0] pixel_in;
    wire valid_out, h_sync_out, v_sync_out;
    wire[PIXEL_W-1:0] pixel_out;

    LSC #(
        .PIXEL_W(PIXEL_W),
        .LINE_W(LINE_W),
        .FRAME_W(FRAME_W),
        .C2_R(C2_R),
        .C2_Gr(C2_Gr),
        .C2_Gb(C2_Gb),
        .C2_B(C2_B)
    ) DUT (
        .clk(clk),
        .resetn(resetn),
        .valid_in(valid_in),
        .h_sync(h_sync),
        .v_sync(v_sync),
        .pixel_in(pixel_in),
        .valid_out(valid_out),
        .h_sync_out(h_sync_out),
        .v_sync_out(v_sync_out),
        .pixel_out(pixel_out)
    );

    initial clk = 0;
    always #1.5 clk = ~clk;

    task send_pixel;
        input [PIXEL_W-1:0] data;
        input [31:0] count_h;
        begin
            pixel_in = data;
            valid_in = 1;
            h_sync   = (count_h < LINE_W-1) ? 1 : 0; 
        end
    endtask

    reg[31:0] tb_x, tb_y;
    reg[PIXEL_W-1:0] exp_p0, exp_p1, exp_p2, exp_p3, exp_p4, exp_p5, exp_p6;
    
    integer match_count;
    integer error_count;
    integer i, j;
    reg[PIXEL_W-1:0] data;

    reg[31:0] mx, my, dx, dy;
    reg[63:0] r2_val;
    reg[1:0]  sel;
    reg[31:0] c2_val;
    reg[63:0] g_val;
    reg[63:0] prod_val;
    reg[63:0] shift_val;
    reg[PIXEL_W-1:0] clamp_val;

    always @(posedge clk or negedge resetn) begin
        if (!resetn) begin
            tb_x   <= 0;
            tb_y   <= 0;
            exp_p0 <= 0;
            exp_p1 <= 0;
            exp_p2 <= 0;
            exp_p3 <= 0;
            exp_p4 <= 0;
            exp_p5 <= 0;
            exp_p6 <= 0;
        end 
        else if (v_sync) begin
            tb_x   <= 0;
            tb_y   <= 0;
        end 
        else begin
            exp_p1 <= exp_p0;
            exp_p2 <= exp_p1;
            exp_p3 <= exp_p2;
            exp_p4 <= exp_p3;
            exp_p5 <= exp_p4;
            exp_p6 <= exp_p5;
            
            if(valid_in) begin
                mx = LINE_W / 2;
                my = FRAME_W / 2;
                dx = (tb_x <= mx) ? (mx - tb_x) : (tb_x - mx);
                dy = (tb_y <= my) ? (my - tb_y) : (tb_y - my);
                r2_val = (dx * dx) + (dy * dy);
                sel = {tb_y[0], tb_x[0]};
                
                if(sel == 2'b00)       
                    c2_val = C2_R;
                else if(sel == 2'b01)  
                    c2_val = C2_Gr;
                else if(sel == 2'b10)  
                    c2_val = C2_Gb;
                else                   
                    c2_val = C2_B;
                
                g_val = (1'b1 << 24) + (c2_val * r2_val);
                prod_val = g_val * pixel_in;
                shift_val = prod_val >> 24;
                
                if(shift_val > ((1 << PIXEL_W) - 1)) begin
                    clamp_val = ((1 << PIXEL_W) - 1);
                end 
                else begin
                    clamp_val = shift_val[PIXEL_W-1:0];
                end
                
                exp_p0 <= clamp_val;

                if(tb_x == LINE_W - 1) begin
                    tb_x <= 0;
                    tb_y <= tb_y + 1;
                end 
                else begin
                    tb_x <= tb_x + 1;
                end
            end
        end
    end

    always@(posedge clk) begin
        if(resetn && valid_out) begin
            if(pixel_out === exp_p6) begin
                match_count = match_count + 1;
            end 
            else begin
                $display("[MISMATCH] Time: %0t | Expected: %d, Got: %d", $time, exp_p6, pixel_out);
                error_count = error_count + 1;
            end
        end
    end

    initial begin
        match_count = 0;
        error_count = 0;
        resetn      = 0;
        pixel_in    = 0;
        valid_in    = 0;
        h_sync      = 0;
        v_sync      = 0;
        data        = 0;
        repeat(2)@(posedge clk);
        
        resetn = 1;
        repeat(2)@(posedge clk);
        
        v_sync = 1;
        @(posedge clk);
        v_sync = 0;
        
        for(i = 0; i < FRAME_W; i = i + 1) begin
            for(j = 0; j < LINE_W; j = j + 1) begin
                data = $random & {PIXEL_W{1'b1}};
                send_pixel(data, j);
                @(posedge clk);
            end
            valid_in = 0;
            h_sync   = 0;
            repeat(5)@(posedge clk); 
        end

        valid_in = 0;
        h_sync   = 0;
        repeat(10)@(posedge clk); 

        $display("\n--- SIMULATION REPORT ---");
        $display("Matches: %0d", match_count);
        $display("Errors:  %0d", error_count);
        if(error_count == 0 && match_count > 0) begin
            $display("STATUS:  PASSED");
        end 
        else begin
            $display("STATUS:  FAILED");
        end
        $display("-------------------------\n");

        $finish;
    end
    
    initial begin
        $dumpfile("lsc_trace.vcd");
        $dumpvars(0, lsc_tb);
    end
endmodule

MODULES/LSC/RTL/lsc_trace.vcd
$date
	Mon Jul  6 08:57:55 2026
$end
$version
	Icarus Verilog
$end
$timescale
	1ps
$end
$scope module lsc_tb $end
$var wire 1 ! valid_out $end
$var wire 1 " v_sync_out $end
$var wire 10 # pixel_out [9:0] $end
$var wire 1 $ h_sync_out $end
$var parameter 32 % C2_B $end
$var parameter 32 & C2_Gb $end
$var parameter 32 ' C2_Gr $end
$var parameter 32 ( C2_R $end
$var parameter 32 ) FRAME_W $end
$var parameter 32 * LINE_W $end
$var parameter 32 + PIXEL_W $end
$var reg 32 , c2_val [31:0] $end
$var reg 10 - clamp_val [9:0] $end
$var reg 1 . clk $end
$var reg 10 / data [9:0] $end
$var reg 32 0 dx [31:0] $end
$var reg 32 1 dy [31:0] $end
$var reg 10 2 exp_p0 [9:0] $end
$var reg 10 3 exp_p1 [9:0] $end
$var reg 10 4 exp_p2 [9:0] $end
$var reg 10 5 exp_p3 [9:0] $end
$var reg 10 6 exp_p4 [9:0] $end
$var reg 10 7 exp_p5 [9:0] $end
$var reg 10 8 exp_p6 [9:0] $end
$var reg 64 9 g_val [63:0] $end
$var reg 1 : h_sync $end
$var reg 32 ; mx [31:0] $end
$var reg 32 < my [31:0] $end
$var reg 10 = pixel_in [9:0] $end
$var reg 64 > prod_val [63:0] $end
$var reg 64 ? r2_val [63:0] $end
$var reg 1 @ resetn $end
$var reg 2 A sel [1:0] $end
$var reg 64 B shift_val [63:0] $end
$var reg 32 C tb_x [31:0] $end
$var reg 32 D tb_y [31:0] $end
$var reg 1 E v_sync $end
$var reg 1 F valid_in $end
$var integer 32 G error_count [31:0] $end
$var integer 32 H i [31:0] $end
$var integer 32 I j [31:0] $end
$var integer 32 J match_count [31:0] $end
$scope module DUT $end
$var wire 1 . clk $end
$var wire 1 : h_sync $end
$var wire 10 K pixel_in [9:0] $end
$var wire 1 @ resetn $end
$var wire 1 E v_sync $end
$var wire 1 F valid_in $end
$var wire 54 L shifted [53:0] $end
$var wire 10 M clamped_pixel [9:0] $end
$var parameter 32 N C2_B $end
$var parameter 32 O C2_Gb $end
$var parameter 32 P C2_Gr $end
$var parameter 32 Q C2_R $end
$var parameter 32 R DELAY $end
$var parameter 32 S DX_W $end
$var parameter 32 T DY_W $end
$var parameter 32 U FP_SHIFT $end
$var parameter 32 V FRAME_CNT $end
$var parameter 32 W FRAME_W $end
$var parameter 34 X GAIN_W $end
$var parameter 32 Y LINE_CNT $end
$var parameter 32 Z LINE_W $end
$var parameter 10 [ MAX_VAL $end
$var parameter 32 \ MID_X $end
$var parameter 32 ] MID_Y $end
$var parameter 32 ^ PIXEL_W $end
$var parameter 33 _ R2_W $end
$var parameter 33 ` X2_W $end
$var parameter 33 a Y2_W $end
$var reg 44 b gain [43:0] $end
$var reg 1 $ h_sync_out $end
$var reg 6 c hsync_pipe [5:0] $end
$var reg 10 d pixel_out [9:0] $end
$var reg 54 e product [53:0] $end
$var reg 20 f r2 [19:0] $end
$var reg 21 g r2_B [20:0] $end
$var reg 21 h r2_Gb [20:0] $end
$var reg 21 i r2_Gr [20:0] $end
$var reg 21 j r2_R [20:0] $end
$var reg 1 " v_sync_out $end
$var reg 1 ! valid_out $end
$var reg 6 k valid_pipe [5:0] $end
$var reg 6 l vsync_pipe [5:0] $end
$var reg 19 m x2 [18:0] $end
$var reg 10 n x_count [9:0] $end
$var reg 10 o x_dist [9:0] $end
$var reg 3 p y2 [2:0] $end
$var reg 2 q y_count [1:0] $end
$var reg 2 r y_dist [1:0] $end
$var integer 32 s i [31:0] $end
$upscope $end
$scope task send_pixel $end
$var reg 32 t count_h [31:0] $end
$var reg 10 u data [9:0] $end
$upscope $end
$upscope $end
$enddefinitions $end
$comment Show the parameter values. $end
$dumpall
b11 a
b10011 `
b10100 _
b1010 ^
b10 ]
b1000000000 \
b1111111111 [
b10000000000 Z
b1010 Y
b101100 X
b100 W
b10 V
b11000 U
b10 T
b1010 S
b110 R
b10 Q
b10 P
b10 O
b10 N
b1010 +
b10000000000 *
b100 )
b10 (
b10 '
b10 &
b10 %
$end
#0
$dumpvars
bx u
bx t
b101 s
b0 r
b0 q
bx p
b0 o
b0 n
bx m
b0 l
b0 k
bx j
bx i
bx h
bx g
b0 f
bx e
b0 d
b0 c
b0 b
bx M
b0xxxxxxxxxxxxxxxxxxxxxxxxxxxxxx L
b0 K
b0 J
bx I
bx H
b0 G
0F
0E
b0 D
b0 C
bx B
bx A
0@
bx ?
bx >
b0 =
bx <
bx ;
0:
bx 9
b0 8
b0 7
b0 6
b0 5
b0 4
b0 3
b0 2
bx 1
bx 0
b0 /
0.
bx -
bx ,
0$
b0 #
0"
0!
$end
#1500
b101 s
1.
#3000
0.
#4500
b0 s
1@
1.
#6000
0.
#7500
b0 s
1.
#9000
0.
#10500
b1 l
b0 s
1E
1.
#12000
0.
#13500
b1 C
b100101101 2
b10 r
b1000000000 o
b10 l
b1 c
b1 k
b1 n
b100101101 -
b100101101 B
b100101101001000000000100100100000 >
b1000010000000000000001000 9
b10 ,
b0 A
b1000000000000000100 ?
b10 1
b1000000000 0
b10 <
b1000000000 ;
b0 s
1:
1F
b100100100 =
b100100100 K
b0 t
b100100100 u
b100100100 /
b0 I
b0 H
0E
1.
#15000
0.
#16500
b10 n
b100 p
b1000000000000000000 m
b111111111 o
b100 l
b11 c
b11 k
b10 C
b1010010100 2
b100101101 3
b0 s
b1010010100 -
b1010010100 B
b1010010100111101000001000100001010 >
b1000001111111100000001010 9
b1 A
b111111110000000101 ?
b111111111 0
b1010000001 =
b1010000001 K
b1 t
b1010000001 u
b1010000001 /
b1 I
1.
#18000
0.
#19500
b11 C
b1000011001 2
b100101101 4
b1010010100 3
b1000000000000000100 f
b111111110000000001 m
b111111110 o
b1000 l
b111 c
b111 k
b11 n
b1000011001 -
b1000011001 B
b1000011001001001111001000010010000 >
b1000001111111000000010000 9
b0 A
b111111100000001000 ?
b111111110 0
b0 s
b1000001001 =
b1000001001 K
b10 t
b1000001001 u
b1000001001 /
b10 I
1.
#21000
0.
#22500
b100 n
b10000000000000001000 g
b10000000000000001000 h
b10000000000000001000 i
b10000000000000001000 j
b111111110000000101 f
b111111100000000100 m
b111111101 o
b10000 l
b1111 c
b1111 k
b100 C
b1001110101 2
b100101101 5
b1010010100 4
b1000011001 3
b0 s
b1001110101 -
b1001110101 B
b1001110101110111101111011000001110 >
b1000001111110100000011010 9
b1 A
b111111010000001101 ?
b111111101 0
b1001100011 =
b1001100011 K
b11 t
b1001100011 u
b1001100011 /
b11 I
1.
#24000
0.
#25500
b101 C
b1100100101 2
b100101101 6
b1010010100 5
b1000011001 4
b1001110101 3
b1000010000000000000001000 b
b1111111100000001010 g
b1111111100000001010 h
b1111111100000001010 i
b1111111100000001010 j
b111111100000001000 f
b111111010000001001 m
b111111100 o
b100000 l
b11111 c
b11111 k
b101 n
b1100100101 -
b1100100101 B
b1100100101000001101101101000001000 >
b1000001111110000000101000 9
b0 A
b111111000000010100 ?
b111111100 0
b0 s
b1100001101 =
b1100001101 K
b100 t
b1100001101 u
b1100001101 /
b100 I
1.
#27000
0.
#28500
b100101101 M
b100101101 L
b110 n
b100101101001000000000100100100000 e
b1000001111111100000001010 b
b1111111000000010000 g
b1111111000000010000 h
b1111111000000010000 i
b1111111000000010000 j
b111111010000001101 f
b111111000000010000 m
b111111011 o
1"
b0 l
b111111 c
b111111 k
b110 C
b110011001 2
b100101101 7
b1010010100 6
b1000011001 5
b1001110101 4
b1100100101 3
b0 s
b110011001 -
b110011001 B
b110011001001010100101000111110010 >
b1000001111101100000111010 9
b1 A
b111110110000011101 ?
b111111011 0
b110001101 =
b110001101 K
b101 t
b110001101 u
b110001101 /
b101 I
1.
#30000
0.
#31500
b1010010100 M
b1010010100 L
b111 C
b1101000 2
b100101101 8
b1010010100 7
b1000011001 6
b1001110101 5
b1100100101 4
b110011001 3
b100101101 #
b100101101 d
b1010010100111101000001000100001010 e
b1000001111111000000010000 b
b1111110100000011010 g
b1111110100000011010 h
b1111110100000011010 i
b1111110100000011010 j
b111111000000010100 f
b111110110000011001 m
b111111010 o
0"
1$
1!
b111 n
b1101000 -
b1101000 B
b1101000000101010010111110010000 >
b1000001111101000001010000 9
b0 A
b111110100000101000 ?
b111111010 0
b0 s
b1100101 =
b1100101 K
b110 t
b1100101 u
b1100101 /
b110 I
1.
#33000
0.
#34500
b1000011001 M
b1000011001 L
b1000 n
b1010010100 #
b1010010100 d
b1000011001001001111001000010010000 e
b1000001111110100000011010 b
b1111110000000101000 g
b1111110000000101000 h
b1111110000000101000 i
b1111110000000101000 j
b111110110000011101 f
b111110100000100100 m
b111111001 o
b1000 C
b1000100010 2
b1010010100 8
b1000011001 7
b1001110101 6
b1100100101 5
b110011001 4
b1101000 3
b0 s
b1000100010 -
b1000100010 B
b1000100010000111001110101101110100 >
b1000001111100100001101010 9
b1 A
b111110010000110101 ?
b111111001 0
b1000010010 =
b1000010010 K
b1 J
b111 t
b1000010010 u
b1000010010 /
b111 I
1.
#36000
0.
#37500
b1001110101 M
b1001110101 L
b1001 C
b1100011000 2
b1000011001 8
b1001110101 7
b1100100101 6
b110011001 5
b1101000 4
b1000100010 3
b1000011001 #
b1000011001 d
b1001110101110111101111011000001110 e
b1000001111110000000101000 b
b1111101100000111010 g
b1111101100000111010 h
b1111101100000111010 i
b1111101100000111010 j
b111110100000101000 f
b111110010000110001 m
b111111000 o
b1001 n
b1100011000 -
b1100011000 B
b1100011000010010010101100010001000 >
b1000001111100000010001000 9
b0 A
b111110000001000100 ?
b111111000 0
b0 s
b1100000001 =
b1100000001 K
b10 J
b1000 t
b1100000001 u
b1100000001 /
b1000 I
1.
#39000
0.
#40500
b1100100101 M
b1100100101 L
b1010 n
b1001110101 #
b1001110101 d
b1100100101000001101101101000001000 e
b1000001111101100000111010 b
b1111101000001010000 g
b1111101000001010000 h
b1111101000001010000 i
b1111101000001010000 j
b111110010000110101 f
b111110000001000000 m
b111110111 o
b1010 C
b100010101 2
b1001110101 8
b1100100101 7
b110011001 6
b1101000 5
b1000100010 4
b1100011000 3
b0 s
b100010101 -
b100010101 B
b100010101000111010000101010100010 >
b1000001111011100010101010 9
b1 A
b111101110001010101 ?
b111110111 0
b100001101 =
b100001101 K
b11 J
b1001 t
b100001101 u
b100001101 /
b1001 I
1.
#42000
0.
#43500
b110011001 M
b110011001 L
b1011 C
b110000001 2
b1100100101 8
b110011001 7
b1101000 6
b1000100010 5
b1100011000 4
b100010101 3
b1100100101 #
b1100100101 d
b110011001001010100101000111110010 e
b1000001111101000001010000 b
b1111100100001101010 g
b1111100100001101010 h
b1111100100001101010 i
b1111100100001101010 j
b111110000001000100 f
b111101110001010001 m
b111110110 o
b1011 n
b110000001 -
b110000001 B
b110000001001111000100111111100000 >
b1000001111011000011010000 9
b0 A
b111101100001101000 ?
b111110110 0
b0 s
b101110110 =
b101110110 K
b100 J
b1010 t
b101110110 u
b101110110 /
b1010 I
1.
#45000
0.
#46500
b1101000 M
b1101000 L
b1100 n
b110011001 #
b110011001 d
b1101000000101010010111110010000 e
b1000001111100100001101010 b
b1111100000010001000 g
b1111100000010001000 h
b1111100000010001000 i
b1111100000010001000 j
b111101110001010101 f
b111101100001100100 m
b111110101 o
b1100 C
b101000110 2
b110011001 8
b1101000 7
b1000100010 6
b1100011000 5
b100010101 4
b110000001 3
b0 s
b101000110 -
b101000110 B
b101000110011111000011110110010010 >
b1000001111010100011111010 9
b1 A
b111101010001111101 ?
b111110101 0
b100111101 =
b100111101 K
b101 J
b1011 t
b100111101 u
b100111101 /
b1011 I
1.
#48000
0.
#49500
b1000100010 M
b1000100010 L
b1101 C
b1111111111 2
b1101000 8
b1000100010 7
b1100011000 6
b100010101 5
b110000001 4
b101000110 3
b1101000 #
b1101000 d
b1000100010000111001110101101110100 e
b1000001111100000010001000 b
b1111011100010101010 g
b1111011100010101010 h
b1111011100010101010 i
b1111011100010101010 j
b111101100001101000 f
b111101010001111001 m
b111110100 o
b1101 n
b1111111111 -
b10000001010 B
b10000001010111100111010101000001000 >
b1000001111010000100101000 9
b0 A
b111101000010010100 ?
b111110100 0
b0 s
b1111101101 =
b1111101101 K
b110 J
b1100 t
b1111101101 u
b1111101101 /
b1100 I
1.
#51000
0.
#52500
b1100011000 M
b1100011000 L
b1110 n
b1000100010 #
b1000100010 d
b1100011000010010010101100010001000 e
b1000001111011100010101010 b
b1111011000011010000 g
b1111011000011010000 h
b1111011000011010000 i
b1111011000011010000 j
b111101010001111101 f
b111101000010010000 m
b111110011 o
b1110 C
b1110100110 2
b1000100010 8
b1100011000 7
b100010101 6
b110000001 5
b101000110 4
b1111111111 3
b0 s
b1110100110 -
b1110100110 B
b1110100110111100111110101100111000 >
b1000001111001100101011010 9
b1 A
b111100110010101101 ?
b111110011 0
b1110001100 =
b1110001100 K
b111 J
b1101 t
b1110001100 u
b1110001100 /
b1101 I
1.
#54000
0.
#55500
b100010101 M
b100010101 L
b1111 C
b1000000111 2
b1100011000 8
b100010101 7
b110000001 6
b101000110 5
b1111111111 4
b1110100110 3
b1100011000 #
b1100011000 d
b100010101000111010000101010100010 e
b1000001111011000011010000 b
b1111010100011111010 g
b1111010100011111010 h
b1111010100011111010 i
b1111010100011111010 j
b111101000010010100 f
b111100110010101001 m
b111110010 o
b1111 n
b1000000111 -
b1000000111 B
b1000000111111011100010010100010000 >
b1000001111001000110010000 9
b0 A
b111100100011001000 ?
b111110010 0
b0 s
b111111001 =
b111111001 K
b1000 J
b1110 t
b111111001 u
b111111001 /
b1110 I
1.
#57000
0.
#58500
b110000001 M
b110000001 L
b10000 n
b100010101 #
b100010101 d
b110000001001111000100111111100000 e
b1000001111010100011111010 b
b1111010000100101000 g
b1111010000100101000 h
b1111010000100101000 i
b1111010000100101000 j
b111100110010101101 f
b111100100011000100 m
b111110001 o
b10000 C
b11001011 2
b100010101 8
b110000001 7
b101000110 6
b1111111111 5
b1110100110 4
b1000000111 3
b0 s
b11001011 -
b11001011 B
b11001011110101001001001000111100 >
b1000001111000100111001010 9
b1 A
b111100010011100101 ?
b111110001 0
b11000110 =
b11000110 K
b1001 J
b1111 t
b11000110 u
b11000110 /
b1111 I
1.
#60000
0.
#61500
b101000110 M
b101000110 L
b10001 C
b11001010 2
b110000001 8
b101000110 7
b1111111111 6
b1110100110 5
b1000000111 4
b11001011 3
b110000001 #
b110000001 d
b101000110011111000011110110010010 e
b1000001111010000100101000 b
b1111001100101011010 g
b1111001100101011010 h
b1111001100101011010 i
b1111001100101011010 j
b111100100011001000 f
b111100010011100001 m
b111110000 o
b10001 n
b11001010 -
b11001010 B
b11001010110001110001000000101000 >
b1000001111000001000001000 9
b0 A
b111100000100000100 ?
b111110000 0
b0 s
b11000101 =
b11000101 K
b1010 J
b10000 t
b11000101 u
b11000101 /
b10000 I
1.
#63000
0.
#64500
b1111111111 M
b10000001010 L
b10010 n
b101000110 #
b101000110 d
b10000001010111100111010101000001000 e
b1000001111001100101011010 b
b1111001000110010000 g
b1111001000110010000 h
b1111001000110010000 i
b1111001000110010000 j
b111100010011100101 f
b111100000100000000 m
b111101111 o
b10010 C
b1010111101 2
b101000110 8
b1111111111 7
b1110100110 6
b1000000111 5
b11001011 4
b11001010 3
b0 s
b1010111101 -
b1010111101 B
b1010111101111010111100100100100100 >
b1000001110111101001001010 9
b1 A
b111011110100100101 ?
b111101111 0
b1010101010 =
b1010101010 K
b1011 J
b10001 t
b1010101010 u
b1010101010 /
b10001 I
1.
#66000
0.
#67500
b1110100110 M
b1110100110 L
b10011 C
b1111111111 2
b1111111111 8
b1110100110 7
b1000000111 6
b11001011 5
b11001010 4
b1010111101 3
b1111111111 #
b1111111111 d
b1110100110111100111110101100111000 e
b1000001111001000110010000 b
b1111000100111001010 g
b1111000100111001010 h
b1111000100111001010 i
b1111000100111001010 j
b111100000100000100 f
b111011110100100001 m
b111101110 o
b10011 n
b1111111111 -
b10000000010 B
b10000000010000000010010101011010000 >
b1000001110111001010010000 9
b0 A
b111011100101001000 ?
b111101110 0
b0 s
b1111100101 =
b1111100101 K
b1100 J
b10010 t
b1111100101 u
b1111100101 /
b10010 I
1.
#69000
0.
#70500
b1000000111 M
b1000000111 L
b10100 n
b1110100110 #
b1110100110 d
b1000000111111011100010010100010000 e
b1000001111000100111001010 b
b1111000001000001000 g
b1111000001000001000 h
b1111000001000001000 i
b1111000001000001000 j
b111011110100100101 f
b111011100101000100 m
b111101101 o
b10100 C
b1010001001 2
b1110100110 8
b1000000111 7
b11001011 6
b11001010 5
b1010111101 4
b1111111111 3
b0 s
b1010001001 -
b1010001001 B
b1010001001010010000101111101010110 >
b1000001110110101011011010 9
b1 A
b111011010101101101 ?
b111101101 0
b1001110111 =
b1001110111 K
b1101 J
b10011 t
b1001110111 u
b1001110111 /
b10011 I
1.
#72000
0.
#73500
b11001011 M
b11001011 L
b10101 C
b1000100001 2
b1000000111 8
b11001011 7
b11001010 6
b1010111101 5
b1111111111 4
b1010001001 3
b1000000111 #
b1000000111 d
b11001011110101001001001000111100 e
b1000001111000001000001000 b
b1110111101001001010 g
b1110111101001001010 h
b1110111101001001010 i
b1110111101001001010 j
b111011100101001000 f
b111011010101101001 m
b111101100 o
b10101 n
b1000100001 -
b1000100001 B
b1000100001010010110100100011010000 >
b1000001110110001100101000 9
b0 A
b111011000110010100 ?
b111101100 0
b0 s
b1000010010 =
b1000010010 K
b1110 J
b10100 t
b1000010010 u
b1000010010 /
b10100 I
1.
#75000
0.
#76500
b11001010 M
b11001010 L
b10110 n
b11001011 #
b11001011 d
b11001010110001110001000000101000 e
b1000001110111101001001010 b
b1110111001010010000 g
b1110111001010010000 h
b1110111001010010000 i
b1110111001010010000 j
b111011010101101101 f
b111011000110010000 m
b111101011 o
b10110 C
b1110101001 2
b11001011 8
b11001010 7
b1010111101 6
b1111111111 5
b1010001001 4
b1000100001 3
b0 s
b1110101001 -
b1110101001 B
b1110101001001011101000011100100110 >
b1000001110101101101111010 9
b1 A
b111010110110111101 ?
b111101011 0
b1110001111 =
b1110001111 K
b1111 J
b10101 t
b1110001111 u
b1110001111 /
b10101 I
1.
#78000
0.
#79500
b1010111101 M
b1010111101 L
b10111 C
b1000000000 2
b11001010 8
b1010111101 7
b1111111111 6
b1010001001 5
b1000100001 4
b1110101001 3
b11001010 #
b11001010 d
b1010111101111010111100100100100100 e
b1000001110111001010010000 b
b1110110101011011010 g
b1110110101011011010 h
b1110110101011011010 i
b1110110101011011010 j
b111011000110010100 f
b111010110110111001 m
b111101010 o
b10111 n
b1000000000 -
b1000000000 B
b1000000000010000010000101010100000 >
b1000001110101001111010000 9
b0 A
b111010100111101000 ?
b111101010 0
b0 s
b111110010 =
b111110010 K
b10000 J
b10110 t
b111110010 u
b111110010 /
b10110 I
1.
#81000
0.
#82500
b1111111111 M
b10000000010 L
b11000 n
b1010111101 #
b1010111101 d
b10000000010000000010010101011010000 e
b1000001110110101011011010 b
b1110110001100101000 g
b1110110001100101000 h
b1110110001100101000 i
b1110110001100101000 j
b111010110110111101 f
b111010100111100100 m
b111101001 o
b11000 C
b1011100010 2
b1010111101 8
b1111111111 7
b1010001001 6
b1000100001 5
b1110101001 4
b1000000000 3
b0 s
b1011100010 -
b1011100010 B
b1011100010011101111001110111001100 >
b1000001110100110000101010 9
b1 A
b111010011000010101 ?
b111101001 0
b1011001110 =
b1011001110 K
b10001 J
b10111 t
b1011001110 u
b1011001110 /
b10111 I
1.
#84000
0.
